{
	"name": "Test Map #2 – Huge Forest",
	"entities": [
		{
			"name": "tree",
			"posX": 50,
			"posY": 50,
			"posZ": "over"
		},
		{
			"name": "tree",
			"posX": 120,
			"posY": 50,
			"posZ": "over"
		},
		{
			"name": "tree",
			"posX": 190,
			"posY": 50,
			"posZ": "over"
		},
		{
			"name": "tree",
			"posX": 260,
			"posY": 50,
			"posZ": "over"
		},
		{
			"name": "tree",
			"posX": 330,
			"posY": 50,
			"posZ": "over"
		},
		{
			"name": "tree",
			"posX": 400,
			"posY": 50,
			"posZ": "over"
		},
		{
			"name": "tree",
			"posX": 470,
			"posY": 50,
			"posZ": "over"
		},
		{
			"name": "tree",
			"posX": 540,
			"posY": 50,
			"posZ": "over"
		},
		{
			"name": "tree",
			"posX": 610,
			"posY": 50,
			"posZ": "over"
		},
		{
			"name": "tree",
			"posX": 680,
			"posY": 50,
			"posZ": "over"
		},
		{
			"name": "tree",
			"posX": 750,
			"posY": 50,
			"posZ": "over"
		},
		{
			"name": "tree",
			"posX": 820,
			"posY": 50,
			"posZ": "over"
		},
		{
			"name": "tree",
			"posX": 890,
			"posY": 50,
			"posZ": "over"
		},
		{
			"name": "tree",
			"posX": 960,
			"posY": 50,
			"posZ": "over"
		},
		{
			"name": "tree",
			"posX": 1030,
			"posY": 50,
			"posZ": "over"
		},
		{
			"name": "tree",
			"posX": 1100,
			"posY": 50,
			"posZ": "over"
		},
		{
			"name": "tree",
			"posX": 1170,
			"posY": 50,
			"posZ": "over"
		},
		{
			"name": "tree",
			"posX": 1240,
			"posY": 50,
			"posZ": "over"
		},
		{
			"name": "tree",
			"posX": 1310,
			"posY": 50,
			"posZ": "over"
		},
		{
			"name": "tree",
			"posX": 1380,
			"posY": 50,
			"posZ": "over"
		},
		{
			"name": "tree",
			"posX": 1450,
			"posY": 50,
			"posZ": "over"
		},
		{
			"name": "tree",
			"posX": 1520,
			"posY": 50,
			"posZ": "over"
		},
		{
			"name": "tree",
			"posX": 1590,
			"posY": 50,
			"posZ": "over"
		},
		{
			"name": "tree",
			"posX": 1660,
			"posY": 50,
			"posZ": "over"
		},
		{
			"name": "tree",
			"posX": 1730,
			"posY": 50,
			"posZ": "over"
		},
		{
			"name": "tree",
			"posX": 1800,
			"posY": 50,
			"posZ": "over"
		},
		{
			"name": "tree",
			"posX": 1870,
			"posY": 50,
			"posZ": "over"
		},
		{
			"name": "tree",
			"posX": 1940,
			"posY": 50,
			"posZ": "over"
		},
		{
			"name": "tree",
			"posX": 2010,
			"posY": 50,
			"posZ": "over"
		},
		{
			"name": "tree",
			"posX": 2080,
			"posY": 50,
			"posZ": "over"
		},
		{
			"name": "tree",
			"posX": 2150,
			"posY": 50,
			"posZ": "over"
		},
		{
			"name": "tree",
			"posX": 2220,
			"posY": 50,
			"posZ": "over"
		},
		{
			"name": "tree",
			"posX": 2290,
			"posY": 50,
			"posZ": "over"
		},
		{
			"name": "tree",
			"posX": 2360,
			"posY": 50,
			"posZ": "over"
		},
		{
			"name": "tree",
			"posX": 2430,
			"posY": 50,
			"posZ": "over"
		},
		{
			"name": "tree",
			"posX": 2500,
			"posY": 50,
			"posZ": "over"
		},
		{
			"name": "tree",
			"posX": 2570,
			"posY": 50,
			"posZ": "over"
		},
		{
			"name": "tree",
			"posX": 2640,
			"posY": 50,
			"posZ": "over"
		},
		{
			"name": "tree",
			"posX": 2710,
			"posY": 50,
			"posZ": "over"
		},
		{
			"name": "tree",
			"posX": 2780,
			"posY": 50,
			"posZ": "over"
		},
		{
			"name": "tree",
			"posX": 2850,
			"posY": 50,
			"posZ": "over"
		},
		{
			"name": "tree",
			"posX": 2920,
			"posY": 50,
			"posZ": "over"
		},
		{
			"name": "tree",
			"posX": 2990,
			"posY": 50,
			"posZ": "over"
		},
		{
			"name": "tree",
			"posX": 3060,
			"posY": 50,
			"posZ": "over"
		},
		{
			"name": "tree",
			"posX": 3130,
			"posY": 50,
			"posZ": "over"
		},
		{
			"name": "tree",
			"posX": 3200,
			"posY": 50,
			"posZ": "over"
		},
		{
			"name": "tree",
			"posX": 3270,
			"posY": 50,
			"posZ": "over"
		},
		{
			"name": "tree",
			"posX": 3340,
			"posY": 50,
			"posZ": "over"
		},
		{
			"name": "tree",
			"posX": 3410,
			"posY": 50,
			"posZ": "over"
		},
		{
			"name": "tree",
			"posX": 3480,
			"posY": 50,
			"posZ": "over"
		},
		{
			"name": "tree",
			"posX": 3550,
			"posY": 50,
			"posZ": "over"
		},
		{
			"name": "tree",
			"posX": 3620,
			"posY": 50,
			"posZ": "over"
		},
		{
			"name": "tree",
			"posX": 3690,
			"posY": 50,
			"posZ": "over"
		},
		{
			"name": "tree",
			"posX": 3760,
			"posY": 50,
			"posZ": "over"
		},
		{
			"name": "tree",
			"posX": 3830,
			"posY": 50,
			"posZ": "over"
		},
		{
			"name": "tree",
			"posX": 3900,
			"posY": 50,
			"posZ": "over"
		},
		{
			"name": "tree",
			"posX": 3970,
			"posY": 50,
			"posZ": "over"
		},
		{
			"name": "tree",
			"posX": 4040,
			"posY": 50,
			"posZ": "over"
		},
		{
			"name": "tree",
			"posX": 4110,
			"posY": 50,
			"posZ": "over"
		},
		{
			"name": "tree",
			"posX": 4180,
			"posY": 50,
			"posZ": "over"
		},
		{
			"name": "tree",
			"posX": 4250,
			"posY": 50,
			"posZ": "over"
		},
		{
			"name": "tree",
			"posX": 4320,
			"posY": 50,
			"posZ": "over"
		},
		{
			"name": "tree",
			"posX": 4390,
			"posY": 50,
			"posZ": "over"
		},
		{
			"name": "tree",
			"posX": 4460,
			"posY": 50,
			"posZ": "over"
		},
		{
			"name": "tree",
			"posX": 4530,
			"posY": 50,
			"posZ": "over"
		},
		{
			"name": "tree",
			"posX": 4600,
			"posY": 50,
			"posZ": "over"
		},
		{
			"name": "tree",
			"posX": 4670,
			"posY": 50,
			"posZ": "over"
		},
		{
			"name": "tree",
			"posX": 4740,
			"posY": 50,
			"posZ": "over"
		},
		{
			"name": "tree",
			"posX": 4810,
			"posY": 50,
			"posZ": "over"
		},
		{
			"name": "tree",
			"posX": 4880,
			"posY": 50,
			"posZ": "over"
		},
		{
			"name": "tree",
			"posX": 4950,
			"posY": 50,
			"posZ": "over"
		},
		{
			"name": "tree",
			"posX": 5020,
			"posY": 50,
			"posZ": "over"
		},
		{
			"name": "tree",
			"posX": 5090,
			"posY": 50,
			"posZ": "over"
		},
		{
			"name": "tree",
			"posX": 5160,
			"posY": 50,
			"posZ": "over"
		},
		{
			"name": "tree",
			"posX": 5230,
			"posY": 50,
			"posZ": "over"
		},
		{
			"name": "tree",
			"posX": 5300,
			"posY": 50,
			"posZ": "over"
		},
		{
			"name": "tree",
			"posX": 5370,
			"posY": 50,
			"posZ": "over"
		},
		{
			"name": "tree",
			"posX": 5440,
			"posY": 50,
			"posZ": "over"
		},
		{
			"name": "tree",
			"posX": 5510,
			"posY": 50,
			"posZ": "over"
		},
		{
			"name": "tree",
			"posX": 5580,
			"posY": 50,
			"posZ": "over"
		},
		{
			"name": "tree",
			"posX": 5650,
			"posY": 50,
			"posZ": "over"
		},
		{
			"name": "tree",
			"posX": 5720,
			"posY": 50,
			"posZ": "over"
		},
		{
			"name": "tree",
			"posX": 5790,
			"posY": 50,
			"posZ": "over"
		},
		{
			"name": "tree",
			"posX": 5860,
			"posY": 50,
			"posZ": "over"
		},
		{
			"name": "tree",
			"posX": 5930,
			"posY": 50,
			"posZ": "over"
		},
		{
			"name": "tree",
			"posX": 6000,
			"posY": 50,
			"posZ": "over"
		},
		{
			"name": "tree",
			"posX": 6070,
			"posY": 50,
			"posZ": "over"
		},
		{
			"name": "tree",
			"posX": 6140,
			"posY": 50,
			"posZ": "over"
		},
		{
			"name": "tree",
			"posX": 6210,
			"posY": 50,
			"posZ": "over"
		},
		{
			"name": "tree",
			"posX": 6280,
			"posY": 50,
			"posZ": "over"
		},
		{
			"name": "tree",
			"posX": 6350,
			"posY": 50,
			"posZ": "over"
		},
		{
			"name": "tree",
			"posX": 6420,
			"posY": 50,
			"posZ": "over"
		},
		{
			"name": "tree",
			"posX": 6490,
			"posY": 50,
			"posZ": "over"
		},
		{
			"name": "tree",
			"posX": 6560,
			"posY": 50,
			"posZ": "over"
		},
		{
			"name": "tree",
			"posX": 6630,
			"posY": 50,
			"posZ": "over"
		},
		{
			"name": "tree",
			"posX": 6700,
			"posY": 50,
			"posZ": "over"
		},
		{
			"name": "tree",
			"posX": 6770,
			"posY": 50,
			"posZ": "over"
		},
		{
			"name": "tree",
			"posX": 6840,
			"posY": 50,
			"posZ": "over"
		},
		{
			"name": "tree",
			"posX": 6910,
			"posY": 50,
			"posZ": "over"
		},
		{
			"name": "tree",
			"posX": 6980,
			"posY": 50,
			"posZ": "over"
		},
		{
			"name": "tree",
			"posX": 7050,
			"posY": 50,
			"posZ": "over"
		},
		{
			"name": "tree",
			"posX": 85,
			"posY": 120,
			"posZ": "over"
		},
		{
			"name": "tree",
			"posX": 155,
			"posY": 120,
			"posZ": "over"
		},
		{
			"name": "tree",
			"posX": 225,
			"posY": 120,
			"posZ": "over"
		},
		{
			"name": "tree",
			"posX": 295,
			"posY": 120,
			"posZ": "over"
		},
		{
			"name": "tree",
			"posX": 365,
			"posY": 120,
			"posZ": "over"
		},
		{
			"name": "tree",
			"posX": 435,
			"posY": 120,
			"posZ": "over"
		},
		{
			"name": "tree",
			"posX": 505,
			"posY": 120,
			"posZ": "over"
		},
		{
			"name": "tree",
			"posX": 575,
			"posY": 120,
			"posZ": "over"
		},
		{
			"name": "tree",
			"posX": 645,
			"posY": 120,
			"posZ": "over"
		},
		{
			"name": "tree",
			"posX": 715,
			"posY": 120,
			"posZ": "over"
		},
		{
			"name": "tree",
			"posX": 785,
			"posY": 120,
			"posZ": "over"
		},
		{
			"name": "tree",
			"posX": 855,
			"posY": 120,
			"posZ": "over"
		},
		{
			"name": "tree",
			"posX": 925,
			"posY": 120,
			"posZ": "over"
		},
		{
			"name": "tree",
			"posX": 995,
			"posY": 120,
			"posZ": "over"
		},
		{
			"name": "tree",
			"posX": 1065,
			"posY": 120,
			"posZ": "over"
		},
		{
			"name": "tree",
			"posX": 1135,
			"posY": 120,
			"posZ": "over"
		},
		{
			"name": "tree",
			"posX": 1205,
			"posY": 120,
			"posZ": "over"
		},
		{
			"name": "tree",
			"posX": 1275,
			"posY": 120,
			"posZ": "over"
		},
		{
			"name": "tree",
			"posX": 1345,
			"posY": 120,
			"posZ": "over"
		},
		{
			"name": "tree",
			"posX": 1415,
			"posY": 120,
			"posZ": "over"
		},
		{
			"name": "tree",
			"posX": 1485,
			"posY": 120,
			"posZ": "over"
		},
		{
			"name": "tree",
			"posX": 1555,
			"posY": 120,
			"posZ": "over"
		},
		{
			"name": "tree",
			"posX": 1625,
			"posY": 120,
			"posZ": "over"
		},
		{
			"name": "tree",
			"posX": 1695,
			"posY": 120,
			"posZ": "over"
		},
		{
			"name": "tree",
			"posX": 1765,
			"posY": 120,
			"posZ": "over"
		},
		{
			"name": "tree",
			"posX": 1835,
			"posY": 120,
			"posZ": "over"
		},
		{
			"name": "tree",
			"posX": 1905,
			"posY": 120,
			"posZ": "over"
		},
		{
			"name": "tree",
			"posX": 1975,
			"posY": 120,
			"posZ": "over"
		},
		{
			"name": "tree",
			"posX": 2045,
			"posY": 120,
			"posZ": "over"
		},
		{
			"name": "tree",
			"posX": 2115,
			"posY": 120,
			"posZ": "over"
		},
		{
			"name": "tree",
			"posX": 2185,
			"posY": 120,
			"posZ": "over"
		},
		{
			"name": "tree",
			"posX": 2255,
			"posY": 120,
			"posZ": "over"
		},
		{
			"name": "tree",
			"posX": 2325,
			"posY": 120,
			"posZ": "over"
		},
		{
			"name": "tree",
			"posX": 2395,
			"posY": 120,
			"posZ": "over"
		},
		{
			"name": "tree",
			"posX": 2465,
			"posY": 120,
			"posZ": "over"
		},
		{
			"name": "tree",
			"posX": 2535,
			"posY": 120,
			"posZ": "over"
		},
		{
			"name": "tree",
			"posX": 2605,
			"posY": 120,
			"posZ": "over"
		},
		{
			"name": "tree",
			"posX": 2675,
			"posY": 120,
			"posZ": "over"
		},
		{
			"name": "tree",
			"posX": 2745,
			"posY": 120,
			"posZ": "over"
		},
		{
			"name": "tree",
			"posX": 2815,
			"posY": 120,
			"posZ": "over"
		},
		{
			"name": "tree",
			"posX": 2885,
			"posY": 120,
			"posZ": "over"
		},
		{
			"name": "tree",
			"posX": 2955,
			"posY": 120,
			"posZ": "over"
		},
		{
			"name": "tree",
			"posX": 3025,
			"posY": 120,
			"posZ": "over"
		},
		{
			"name": "tree",
			"posX": 3095,
			"posY": 120,
			"posZ": "over"
		},
		{
			"name": "tree",
			"posX": 3165,
			"posY": 120,
			"posZ": "over"
		},
		{
			"name": "tree",
			"posX": 3235,
			"posY": 120,
			"posZ": "over"
		},
		{
			"name": "tree",
			"posX": 3305,
			"posY": 120,
			"posZ": "over"
		},
		{
			"name": "tree",
			"posX": 3375,
			"posY": 120,
			"posZ": "over"
		},
		{
			"name": "tree",
			"posX": 3445,
			"posY": 120,
			"posZ": "over"
		},
		{
			"name": "tree",
			"posX": 3515,
			"posY": 120,
			"posZ": "over"
		},
		{
			"name": "tree",
			"posX": 3585,
			"posY": 120,
			"posZ": "over"
		},
		{
			"name": "tree",
			"posX": 3655,
			"posY": 120,
			"posZ": "over"
		},
		{
			"name": "tree",
			"posX": 3725,
			"posY": 120,
			"posZ": "over"
		},
		{
			"name": "tree",
			"posX": 3795,
			"posY": 120,
			"posZ": "over"
		},
		{
			"name": "tree",
			"posX": 3865,
			"posY": 120,
			"posZ": "over"
		},
		{
			"name": "tree",
			"posX": 3935,
			"posY": 120,
			"posZ": "over"
		},
		{
			"name": "tree",
			"posX": 4005,
			"posY": 120,
			"posZ": "over"
		},
		{
			"name": "tree",
			"posX": 4075,
			"posY": 120,
			"posZ": "over"
		},
		{
			"name": "tree",
			"posX": 4145,
			"posY": 120,
			"posZ": "over"
		},
		{
			"name": "tree",
			"posX": 4215,
			"posY": 120,
			"posZ": "over"
		},
		{
			"name": "tree",
			"posX": 4285,
			"posY": 120,
			"posZ": "over"
		},
		{
			"name": "tree",
			"posX": 4355,
			"posY": 120,
			"posZ": "over"
		},
		{
			"name": "tree",
			"posX": 4425,
			"posY": 120,
			"posZ": "over"
		},
		{
			"name": "tree",
			"posX": 4495,
			"posY": 120,
			"posZ": "over"
		},
		{
			"name": "tree",
			"posX": 4565,
			"posY": 120,
			"posZ": "over"
		},
		{
			"name": "tree",
			"posX": 4635,
			"posY": 120,
			"posZ": "over"
		},
		{
			"name": "tree",
			"posX": 4705,
			"posY": 120,
			"posZ": "over"
		},
		{
			"name": "tree",
			"posX": 4775,
			"posY": 120,
			"posZ": "over"
		},
		{
			"name": "tree",
			"posX": 4845,
			"posY": 120,
			"posZ": "over"
		},
		{
			"name": "tree",
			"posX": 4915,
			"posY": 120,
			"posZ": "over"
		},
		{
			"name": "tree",
			"posX": 4985,
			"posY": 120,
			"posZ": "over"
		},
		{
			"name": "tree",
			"posX": 5055,
			"posY": 120,
			"posZ": "over"
		},
		{
			"name": "tree",
			"posX": 5125,
			"posY": 120,
			"posZ": "over"
		},
		{
			"name": "tree",
			"posX": 5195,
			"posY": 120,
			"posZ": "over"
		},
		{
			"name": "tree",
			"posX": 5265,
			"posY": 120,
			"posZ": "over"
		},
		{
			"name": "tree",
			"posX": 5335,
			"posY": 120,
			"posZ": "over"
		},
		{
			"name": "tree",
			"posX": 5405,
			"posY": 120,
			"posZ": "over"
		},
		{
			"name": "tree",
			"posX": 5475,
			"posY": 120,
			"posZ": "over"
		},
		{
			"name": "tree",
			"posX": 5545,
			"posY": 120,
			"posZ": "over"
		},
		{
			"name": "tree",
			"posX": 5615,
			"posY": 120,
			"posZ": "over"
		},
		{
			"name": "tree",
			"posX": 5685,
			"posY": 120,
			"posZ": "over"
		},
		{
			"name": "tree",
			"posX": 5755,
			"posY": 120,
			"posZ": "over"
		},
		{
			"name": "tree",
			"posX": 5825,
			"posY": 120,
			"posZ": "over"
		},
		{
			"name": "tree",
			"posX": 5895,
			"posY": 120,
			"posZ": "over"
		},
		{
			"name": "tree",
			"posX": 5965,
			"posY": 120,
			"posZ": "over"
		},
		{
			"name": "tree",
			"posX": 6035,
			"posY": 120,
			"posZ": "over"
		},
		{
			"name": "tree",
			"posX": 6105,
			"posY": 120,
			"posZ": "over"
		},
		{
			"name": "tree",
			"posX": 6175,
			"posY": 120,
			"posZ": "over"
		},
		{
			"name": "tree",
			"posX": 6245,
			"posY": 120,
			"posZ": "over"
		},
		{
			"name": "tree",
			"posX": 6315,
			"posY": 120,
			"posZ": "over"
		},
		{
			"name": "tree",
			"posX": 6385,
			"posY": 120,
			"posZ": "over"
		},
		{
			"name": "tree",
			"posX": 6455,
			"posY": 120,
			"posZ": "over"
		},
		{
			"name": "tree",
			"posX": 6525,
			"posY": 120,
			"posZ": "over"
		},
		{
			"name": "tree",
			"posX": 6595,
			"posY": 120,
			"posZ": "over"
		},
		{
			"name": "tree",
			"posX": 6665,
			"posY": 120,
			"posZ": "over"
		},
		{
			"name": "tree",
			"posX": 6735,
			"posY": 120,
			"posZ": "over"
		},
		{
			"name": "tree",
			"posX": 6805,
			"posY": 120,
			"posZ": "over"
		},
		{
			"name": "tree",
			"posX": 6875,
			"posY": 120,
			"posZ": "over"
		},
		{
			"name": "tree",
			"posX": 6945,
			"posY": 120,
			"posZ": "over"
		},
		{
			"name": "tree",
			"posX": 7015,
			"posY": 120,
			"posZ": "over"
		},
		{
			"name": "tree",
			"posX": 50,
			"posY": 190,
			"posZ": "over"
		},
		{
			"name": "tree",
			"posX": 120,
			"posY": 190,
			"posZ": "over"
		},
		{
			"name": "tree",
			"posX": 190,
			"posY": 190,
			"posZ": "over"
		},
		{
			"name": "tree",
			"posX": 260,
			"posY": 190,
			"posZ": "over"
		},
		{
			"name": "tree",
			"posX": 330,
			"posY": 190,
			"posZ": "over"
		},
		{
			"name": "tree",
			"posX": 400,
			"posY": 190,
			"posZ": "over"
		},
		{
			"name": "tree",
			"posX": 470,
			"posY": 190,
			"posZ": "over"
		},
		{
			"name": "tree",
			"posX": 540,
			"posY": 190,
			"posZ": "over"
		},
		{
			"name": "tree",
			"posX": 610,
			"posY": 190,
			"posZ": "over"
		},
		{
			"name": "tree",
			"posX": 680,
			"posY": 190,
			"posZ": "over"
		},
		{
			"name": "tree",
			"posX": 750,
			"posY": 190,
			"posZ": "over"
		},
		{
			"name": "tree",
			"posX": 820,
			"posY": 190,
			"posZ": "over"
		},
		{
			"name": "tree",
			"posX": 890,
			"posY": 190,
			"posZ": "over"
		},
		{
			"name": "tree",
			"posX": 960,
			"posY": 190,
			"posZ": "over"
		},
		{
			"name": "tree",
			"posX": 1030,
			"posY": 190,
			"posZ": "over"
		},
		{
			"name": "tree",
			"posX": 1100,
			"posY": 190,
			"posZ": "over"
		},
		{
			"name": "tree",
			"posX": 1170,
			"posY": 190,
			"posZ": "over"
		},
		{
			"name": "tree",
			"posX": 1240,
			"posY": 190,
			"posZ": "over"
		},
		{
			"name": "tree",
			"posX": 1310,
			"posY": 190,
			"posZ": "over"
		},
		{
			"name": "tree",
			"posX": 1380,
			"posY": 190,
			"posZ": "over"
		},
		{
			"name": "tree",
			"posX": 1450,
			"posY": 190,
			"posZ": "over"
		},
		{
			"name": "tree",
			"posX": 1520,
			"posY": 190,
			"posZ": "over"
		},
		{
			"name": "tree",
			"posX": 1590,
			"posY": 190,
			"posZ": "over"
		},
		{
			"name": "tree",
			"posX": 1660,
			"posY": 190,
			"posZ": "over"
		},
		{
			"name": "tree",
			"posX": 1730,
			"posY": 190,
			"posZ": "over"
		},
		{
			"name": "tree",
			"posX": 1800,
			"posY": 190,
			"posZ": "over"
		},
		{
			"name": "tree",
			"posX": 1870,
			"posY": 190,
			"posZ": "over"
		},
		{
			"name": "tree",
			"posX": 1940,
			"posY": 190,
			"posZ": "over"
		},
		{
			"name": "tree",
			"posX": 2010,
			"posY": 190,
			"posZ": "over"
		},
		{
			"name": "tree",
			"posX": 2080,
			"posY": 190,
			"posZ": "over"
		},
		{
			"name": "tree",
			"posX": 2150,
			"posY": 190,
			"posZ": "over"
		},
		{
			"name": "tree",
			"posX": 2220,
			"posY": 190,
			"posZ": "over"
		},
		{
			"name": "tree",
			"posX": 2290,
			"posY": 190,
			"posZ": "over"
		},
		{
			"name": "tree",
			"posX": 2360,
			"posY": 190,
			"posZ": "over"
		},
		{
			"name": "tree",
			"posX": 2430,
			"posY": 190,
			"posZ": "over"
		},
		{
			"name": "tree",
			"posX": 2500,
			"posY": 190,
			"posZ": "over"
		},
		{
			"name": "tree",
			"posX": 2570,
			"posY": 190,
			"posZ": "over"
		},
		{
			"name": "tree",
			"posX": 2640,
			"posY": 190,
			"posZ": "over"
		},
		{
			"name": "tree",
			"posX": 2710,
			"posY": 190,
			"posZ": "over"
		},
		{
			"name": "tree",
			"posX": 2780,
			"posY": 190,
			"posZ": "over"
		},
		{
			"name": "tree",
			"posX": 2850,
			"posY": 190,
			"posZ": "over"
		},
		{
			"name": "tree",
			"posX": 2920,
			"posY": 190,
			"posZ": "over"
		},
		{
			"name": "tree",
			"posX": 2990,
			"posY": 190,
			"posZ": "over"
		},
		{
			"name": "tree",
			"posX": 3060,
			"posY": 190,
			"posZ": "over"
		},
		{
			"name": "tree",
			"posX": 3130,
			"posY": 190,
			"posZ": "over"
		},
		{
			"name": "tree",
			"posX": 3200,
			"posY": 190,
			"posZ": "over"
		},
		{
			"name": "tree",
			"posX": 3270,
			"posY": 190,
			"posZ": "over"
		},
		{
			"name": "tree",
			"posX": 3340,
			"posY": 190,
			"posZ": "over"
		},
		{
			"name": "tree",
			"posX": 3410,
			"posY": 190,
			"posZ": "over"
		},
		{
			"name": "tree",
			"posX": 3480,
			"posY": 190,
			"posZ": "over"
		},
		{
			"name": "tree",
			"posX": 3550,
			"posY": 190,
			"posZ": "over"
		},
		{
			"name": "tree",
			"posX": 3620,
			"posY": 190,
			"posZ": "over"
		},
		{
			"name": "tree",
			"posX": 3690,
			"posY": 190,
			"posZ": "over"
		},
		{
			"name": "tree",
			"posX": 3760,
			"posY": 190,
			"posZ": "over"
		},
		{
			"name": "tree",
			"posX": 3830,
			"posY": 190,
			"posZ": "over"
		},
		{
			"name": "tree",
			"posX": 3900,
			"posY": 190,
			"posZ": "over"
		},
		{
			"name": "tree",
			"posX": 3970,
			"posY": 190,
			"posZ": "over"
		},
		{
			"name": "tree",
			"posX": 4040,
			"posY": 190,
			"posZ": "over"
		},
		{
			"name": "tree",
			"posX": 4110,
			"posY": 190,
			"posZ": "over"
		},
		{
			"name": "tree",
			"posX": 4180,
			"posY": 190,
			"posZ": "over"
		},
		{
			"name": "tree",
			"posX": 4250,
			"posY": 190,
			"posZ": "over"
		},
		{
			"name": "tree",
			"posX": 4320,
			"posY": 190,
			"posZ": "over"
		},
		{
			"name": "tree",
			"posX": 4390,
			"posY": 190,
			"posZ": "over"
		},
		{
			"name": "tree",
			"posX": 4460,
			"posY": 190,
			"posZ": "over"
		},
		{
			"name": "tree",
			"posX": 4530,
			"posY": 190,
			"posZ": "over"
		},
		{
			"name": "tree",
			"posX": 4600,
			"posY": 190,
			"posZ": "over"
		},
		{
			"name": "tree",
			"posX": 4670,
			"posY": 190,
			"posZ": "over"
		},
		{
			"name": "tree",
			"posX": 4740,
			"posY": 190,
			"posZ": "over"
		},
		{
			"name": "tree",
			"posX": 4810,
			"posY": 190,
			"posZ": "over"
		},
		{
			"name": "tree",
			"posX": 4880,
			"posY": 190,
			"posZ": "over"
		},
		{
			"name": "tree",
			"posX": 4950,
			"posY": 190,
			"posZ": "over"
		},
		{
			"name": "tree",
			"posX": 5020,
			"posY": 190,
			"posZ": "over"
		},
		{
			"name": "tree",
			"posX": 5090,
			"posY": 190,
			"posZ": "over"
		},
		{
			"name": "tree",
			"posX": 5160,
			"posY": 190,
			"posZ": "over"
		},
		{
			"name": "tree",
			"posX": 5230,
			"posY": 190,
			"posZ": "over"
		},
		{
			"name": "tree",
			"posX": 5300,
			"posY": 190,
			"posZ": "over"
		},
		{
			"name": "tree",
			"posX": 5370,
			"posY": 190,
			"posZ": "over"
		},
		{
			"name": "tree",
			"posX": 5440,
			"posY": 190,
			"posZ": "over"
		},
		{
			"name": "tree",
			"posX": 5510,
			"posY": 190,
			"posZ": "over"
		},
		{
			"name": "tree",
			"posX": 5580,
			"posY": 190,
			"posZ": "over"
		},
		{
			"name": "tree",
			"posX": 5650,
			"posY": 190,
			"posZ": "over"
		},
		{
			"name": "tree",
			"posX": 5720,
			"posY": 190,
			"posZ": "over"
		},
		{
			"name": "tree",
			"posX": 5790,
			"posY": 190,
			"posZ": "over"
		},
		{
			"name": "tree",
			"posX": 5860,
			"posY": 190,
			"posZ": "over"
		},
		{
			"name": "tree",
			"posX": 5930,
			"posY": 190,
			"posZ": "over"
		},
		{
			"name": "tree",
			"posX": 6000,
			"posY": 190,
			"posZ": "over"
		},
		{
			"name": "tree",
			"posX": 6070,
			"posY": 190,
			"posZ": "over"
		},
		{
			"name": "tree",
			"posX": 6140,
			"posY": 190,
			"posZ": "over"
		},
		{
			"name": "tree",
			"posX": 6210,
			"posY": 190,
			"posZ": "over"
		},
		{
			"name": "tree",
			"posX": 6280,
			"posY": 190,
			"posZ": "over"
		},
		{
			"name": "tree",
			"posX": 6350,
			"posY": 190,
			"posZ": "over"
		},
		{
			"name": "tree",
			"posX": 6420,
			"posY": 190,
			"posZ": "over"
		},
		{
			"name": "tree",
			"posX": 6490,
			"posY": 190,
			"posZ": "over"
		},
		{
			"name": "tree",
			"posX": 6560,
			"posY": 190,
			"posZ": "over"
		},
		{
			"name": "tree",
			"posX": 6630,
			"posY": 190,
			"posZ": "over"
		},
		{
			"name": "tree",
			"posX": 6700,
			"posY": 190,
			"posZ": "over"
		},
		{
			"name": "tree",
			"posX": 6770,
			"posY": 190,
			"posZ": "over"
		},
		{
			"name": "tree",
			"posX": 6840,
			"posY": 190,
			"posZ": "over"
		},
		{
			"name": "tree",
			"posX": 6910,
			"posY": 190,
			"posZ": "over"
		},
		{
			"name": "tree",
			"posX": 6980,
			"posY": 190,
			"posZ": "over"
		},
		{
			"name": "tree",
			"posX": 7050,
			"posY": 190,
			"posZ": "over"
		},
		{
			"name": "tree",
			"posX": 85,
			"posY": 260,
			"posZ": "over"
		},
		{
			"name": "tree",
			"posX": 155,
			"posY": 260,
			"posZ": "over"
		},
		{
			"name": "tree",
			"posX": 225,
			"posY": 260,
			"posZ": "over"
		},
		{
			"name": "tree",
			"posX": 295,
			"posY": 260,
			"posZ": "over"
		},
		{
			"name": "tree",
			"posX": 365,
			"posY": 260,
			"posZ": "over"
		},
		{
			"name": "tree",
			"posX": 435,
			"posY": 260,
			"posZ": "over"
		},
		{
			"name": "tree",
			"posX": 505,
			"posY": 260,
			"posZ": "over"
		},
		{
			"name": "tree",
			"posX": 575,
			"posY": 260,
			"posZ": "over"
		},
		{
			"name": "tree",
			"posX": 645,
			"posY": 260,
			"posZ": "over"
		},
		{
			"name": "tree",
			"posX": 715,
			"posY": 260,
			"posZ": "over"
		},
		{
			"name": "tree",
			"posX": 785,
			"posY": 260,
			"posZ": "over"
		},
		{
			"name": "tree",
			"posX": 855,
			"posY": 260,
			"posZ": "over"
		},
		{
			"name": "tree",
			"posX": 925,
			"posY": 260,
			"posZ": "over"
		},
		{
			"name": "tree",
			"posX": 995,
			"posY": 260,
			"posZ": "over"
		},
		{
			"name": "tree",
			"posX": 1065,
			"posY": 260,
			"posZ": "over"
		},
		{
			"name": "tree",
			"posX": 1135,
			"posY": 260,
			"posZ": "over"
		},
		{
			"name": "tree",
			"posX": 1205,
			"posY": 260,
			"posZ": "over"
		},
		{
			"name": "tree",
			"posX": 1275,
			"posY": 260,
			"posZ": "over"
		},
		{
			"name": "tree",
			"posX": 1345,
			"posY": 260,
			"posZ": "over"
		},
		{
			"name": "tree",
			"posX": 1415,
			"posY": 260,
			"posZ": "over"
		},
		{
			"name": "tree",
			"posX": 1485,
			"posY": 260,
			"posZ": "over"
		},
		{
			"name": "tree",
			"posX": 1555,
			"posY": 260,
			"posZ": "over"
		},
		{
			"name": "tree",
			"posX": 1625,
			"posY": 260,
			"posZ": "over"
		},
		{
			"name": "tree",
			"posX": 1695,
			"posY": 260,
			"posZ": "over"
		},
		{
			"name": "tree",
			"posX": 1765,
			"posY": 260,
			"posZ": "over"
		},
		{
			"name": "tree",
			"posX": 1835,
			"posY": 260,
			"posZ": "over"
		},
		{
			"name": "tree",
			"posX": 1905,
			"posY": 260,
			"posZ": "over"
		},
		{
			"name": "tree",
			"posX": 1975,
			"posY": 260,
			"posZ": "over"
		},
		{
			"name": "tree",
			"posX": 2045,
			"posY": 260,
			"posZ": "over"
		},
		{
			"name": "tree",
			"posX": 2115,
			"posY": 260,
			"posZ": "over"
		},
		{
			"name": "tree",
			"posX": 2185,
			"posY": 260,
			"posZ": "over"
		},
		{
			"name": "tree",
			"posX": 2255,
			"posY": 260,
			"posZ": "over"
		},
		{
			"name": "tree",
			"posX": 2325,
			"posY": 260,
			"posZ": "over"
		},
		{
			"name": "tree",
			"posX": 2395,
			"posY": 260,
			"posZ": "over"
		},
		{
			"name": "tree",
			"posX": 2465,
			"posY": 260,
			"posZ": "over"
		},
		{
			"name": "tree",
			"posX": 2535,
			"posY": 260,
			"posZ": "over"
		},
		{
			"name": "tree",
			"posX": 2605,
			"posY": 260,
			"posZ": "over"
		},
		{
			"name": "tree",
			"posX": 2675,
			"posY": 260,
			"posZ": "over"
		},
		{
			"name": "tree",
			"posX": 2745,
			"posY": 260,
			"posZ": "over"
		},
		{
			"name": "tree",
			"posX": 2815,
			"posY": 260,
			"posZ": "over"
		},
		{
			"name": "tree",
			"posX": 2885,
			"posY": 260,
			"posZ": "over"
		},
		{
			"name": "tree",
			"posX": 2955,
			"posY": 260,
			"posZ": "over"
		},
		{
			"name": "tree",
			"posX": 3025,
			"posY": 260,
			"posZ": "over"
		},
		{
			"name": "tree",
			"posX": 3095,
			"posY": 260,
			"posZ": "over"
		},
		{
			"name": "tree",
			"posX": 3165,
			"posY": 260,
			"posZ": "over"
		},
		{
			"name": "tree",
			"posX": 3235,
			"posY": 260,
			"posZ": "over"
		},
		{
			"name": "tree",
			"posX": 3305,
			"posY": 260,
			"posZ": "over"
		},
		{
			"name": "tree",
			"posX": 3375,
			"posY": 260,
			"posZ": "over"
		},
		{
			"name": "tree",
			"posX": 3445,
			"posY": 260,
			"posZ": "over"
		},
		{
			"name": "tree",
			"posX": 3515,
			"posY": 260,
			"posZ": "over"
		},
		{
			"name": "tree",
			"posX": 3585,
			"posY": 260,
			"posZ": "over"
		},
		{
			"name": "tree",
			"posX": 3655,
			"posY": 260,
			"posZ": "over"
		},
		{
			"name": "tree",
			"posX": 3725,
			"posY": 260,
			"posZ": "over"
		},
		{
			"name": "tree",
			"posX": 3795,
			"posY": 260,
			"posZ": "over"
		},
		{
			"name": "tree",
			"posX": 3865,
			"posY": 260,
			"posZ": "over"
		},
		{
			"name": "tree",
			"posX": 3935,
			"posY": 260,
			"posZ": "over"
		},
		{
			"name": "tree",
			"posX": 4005,
			"posY": 260,
			"posZ": "over"
		},
		{
			"name": "tree",
			"posX": 4075,
			"posY": 260,
			"posZ": "over"
		},
		{
			"name": "tree",
			"posX": 4145,
			"posY": 260,
			"posZ": "over"
		},
		{
			"name": "tree",
			"posX": 4215,
			"posY": 260,
			"posZ": "over"
		},
		{
			"name": "tree",
			"posX": 4285,
			"posY": 260,
			"posZ": "over"
		},
		{
			"name": "tree",
			"posX": 4355,
			"posY": 260,
			"posZ": "over"
		},
		{
			"name": "tree",
			"posX": 4425,
			"posY": 260,
			"posZ": "over"
		},
		{
			"name": "tree",
			"posX": 4495,
			"posY": 260,
			"posZ": "over"
		},
		{
			"name": "tree",
			"posX": 4565,
			"posY": 260,
			"posZ": "over"
		},
		{
			"name": "tree",
			"posX": 4635,
			"posY": 260,
			"posZ": "over"
		},
		{
			"name": "tree",
			"posX": 4705,
			"posY": 260,
			"posZ": "over"
		},
		{
			"name": "tree",
			"posX": 4775,
			"posY": 260,
			"posZ": "over"
		},
		{
			"name": "tree",
			"posX": 4845,
			"posY": 260,
			"posZ": "over"
		},
		{
			"name": "tree",
			"posX": 4915,
			"posY": 260,
			"posZ": "over"
		},
		{
			"name": "tree",
			"posX": 4985,
			"posY": 260,
			"posZ": "over"
		},
		{
			"name": "tree",
			"posX": 5055,
			"posY": 260,
			"posZ": "over"
		},
		{
			"name": "tree",
			"posX": 5125,
			"posY": 260,
			"posZ": "over"
		},
		{
			"name": "tree",
			"posX": 5195,
			"posY": 260,
			"posZ": "over"
		},
		{
			"name": "tree",
			"posX": 5265,
			"posY": 260,
			"posZ": "over"
		},
		{
			"name": "tree",
			"posX": 5335,
			"posY": 260,
			"posZ": "over"
		},
		{
			"name": "tree",
			"posX": 5405,
			"posY": 260,
			"posZ": "over"
		},
		{
			"name": "tree",
			"posX": 5475,
			"posY": 260,
			"posZ": "over"
		},
		{
			"name": "tree",
			"posX": 5545,
			"posY": 260,
			"posZ": "over"
		},
		{
			"name": "tree",
			"posX": 5615,
			"posY": 260,
			"posZ": "over"
		},
		{
			"name": "tree",
			"posX": 5685,
			"posY": 260,
			"posZ": "over"
		},
		{
			"name": "tree",
			"posX": 5755,
			"posY": 260,
			"posZ": "over"
		},
		{
			"name": "tree",
			"posX": 5825,
			"posY": 260,
			"posZ": "over"
		},
		{
			"name": "tree",
			"posX": 5895,
			"posY": 260,
			"posZ": "over"
		},
		{
			"name": "tree",
			"posX": 5965,
			"posY": 260,
			"posZ": "over"
		},
		{
			"name": "tree",
			"posX": 6035,
			"posY": 260,
			"posZ": "over"
		},
		{
			"name": "tree",
			"posX": 6105,
			"posY": 260,
			"posZ": "over"
		},
		{
			"name": "tree",
			"posX": 6175,
			"posY": 260,
			"posZ": "over"
		},
		{
			"name": "tree",
			"posX": 6245,
			"posY": 260,
			"posZ": "over"
		},
		{
			"name": "tree",
			"posX": 6315,
			"posY": 260,
			"posZ": "over"
		},
		{
			"name": "tree",
			"posX": 6385,
			"posY": 260,
			"posZ": "over"
		},
		{
			"name": "tree",
			"posX": 6455,
			"posY": 260,
			"posZ": "over"
		},
		{
			"name": "tree",
			"posX": 6525,
			"posY": 260,
			"posZ": "over"
		},
		{
			"name": "tree",
			"posX": 6595,
			"posY": 260,
			"posZ": "over"
		},
		{
			"name": "tree",
			"posX": 6665,
			"posY": 260,
			"posZ": "over"
		},
		{
			"name": "tree",
			"posX": 6735,
			"posY": 260,
			"posZ": "over"
		},
		{
			"name": "tree",
			"posX": 6805,
			"posY": 260,
			"posZ": "over"
		},
		{
			"name": "tree",
			"posX": 6875,
			"posY": 260,
			"posZ": "over"
		},
		{
			"name": "tree",
			"posX": 6945,
			"posY": 260,
			"posZ": "over"
		},
		{
			"name": "tree",
			"posX": 7015,
			"posY": 260,
			"posZ": "over"
		},
		{
			"name": "tree",
			"posX": 50,
			"posY": 330,
			"posZ": "over"
		},
		{
			"name": "tree",
			"posX": 120,
			"posY": 330,
			"posZ": "over"
		},
		{
			"name": "tree",
			"posX": 190,
			"posY": 330,
			"posZ": "over"
		},
		{
			"name": "tree",
			"posX": 260,
			"posY": 330,
			"posZ": "over"
		},
		{
			"name": "tree",
			"posX": 330,
			"posY": 330,
			"posZ": "over"
		},
		{
			"name": "tree",
			"posX": 400,
			"posY": 330,
			"posZ": "over"
		},
		{
			"name": "tree",
			"posX": 470,
			"posY": 330,
			"posZ": "over"
		},
		{
			"name": "tree",
			"posX": 540,
			"posY": 330,
			"posZ": "over"
		},
		{
			"name": "tree",
			"posX": 610,
			"posY": 330,
			"posZ": "over"
		},
		{
			"name": "tree",
			"posX": 680,
			"posY": 330,
			"posZ": "over"
		},
		{
			"name": "tree",
			"posX": 750,
			"posY": 330,
			"posZ": "over"
		},
		{
			"name": "tree",
			"posX": 820,
			"posY": 330,
			"posZ": "over"
		},
		{
			"name": "tree",
			"posX": 890,
			"posY": 330,
			"posZ": "over"
		},
		{
			"name": "tree",
			"posX": 960,
			"posY": 330,
			"posZ": "over"
		},
		{
			"name": "tree",
			"posX": 1030,
			"posY": 330,
			"posZ": "over"
		},
		{
			"name": "tree",
			"posX": 1100,
			"posY": 330,
			"posZ": "over"
		},
		{
			"name": "tree",
			"posX": 1170,
			"posY": 330,
			"posZ": "over"
		},
		{
			"name": "tree",
			"posX": 1240,
			"posY": 330,
			"posZ": "over"
		},
		{
			"name": "tree",
			"posX": 1310,
			"posY": 330,
			"posZ": "over"
		},
		{
			"name": "tree",
			"posX": 1380,
			"posY": 330,
			"posZ": "over"
		},
		{
			"name": "tree",
			"posX": 1450,
			"posY": 330,
			"posZ": "over"
		},
		{
			"name": "tree",
			"posX": 1520,
			"posY": 330,
			"posZ": "over"
		},
		{
			"name": "tree",
			"posX": 1590,
			"posY": 330,
			"posZ": "over"
		},
		{
			"name": "tree",
			"posX": 1660,
			"posY": 330,
			"posZ": "over"
		},
		{
			"name": "tree",
			"posX": 1730,
			"posY": 330,
			"posZ": "over"
		},
		{
			"name": "tree",
			"posX": 1800,
			"posY": 330,
			"posZ": "over"
		},
		{
			"name": "tree",
			"posX": 1870,
			"posY": 330,
			"posZ": "over"
		},
		{
			"name": "tree",
			"posX": 1940,
			"posY": 330,
			"posZ": "over"
		},
		{
			"name": "tree",
			"posX": 2010,
			"posY": 330,
			"posZ": "over"
		},
		{
			"name": "tree",
			"posX": 2080,
			"posY": 330,
			"posZ": "over"
		},
		{
			"name": "tree",
			"posX": 2150,
			"posY": 330,
			"posZ": "over"
		},
		{
			"name": "tree",
			"posX": 2220,
			"posY": 330,
			"posZ": "over"
		},
		{
			"name": "tree",
			"posX": 2290,
			"posY": 330,
			"posZ": "over"
		},
		{
			"name": "tree",
			"posX": 2360,
			"posY": 330,
			"posZ": "over"
		},
		{
			"name": "tree",
			"posX": 2430,
			"posY": 330,
			"posZ": "over"
		},
		{
			"name": "tree",
			"posX": 2500,
			"posY": 330,
			"posZ": "over"
		},
		{
			"name": "tree",
			"posX": 2570,
			"posY": 330,
			"posZ": "over"
		},
		{
			"name": "tree",
			"posX": 2640,
			"posY": 330,
			"posZ": "over"
		},
		{
			"name": "tree",
			"posX": 2710,
			"posY": 330,
			"posZ": "over"
		},
		{
			"name": "tree",
			"posX": 2780,
			"posY": 330,
			"posZ": "over"
		},
		{
			"name": "tree",
			"posX": 2850,
			"posY": 330,
			"posZ": "over"
		},
		{
			"name": "tree",
			"posX": 2920,
			"posY": 330,
			"posZ": "over"
		},
		{
			"name": "tree",
			"posX": 2990,
			"posY": 330,
			"posZ": "over"
		},
		{
			"name": "tree",
			"posX": 3060,
			"posY": 330,
			"posZ": "over"
		},
		{
			"name": "tree",
			"posX": 3130,
			"posY": 330,
			"posZ": "over"
		},
		{
			"name": "tree",
			"posX": 3200,
			"posY": 330,
			"posZ": "over"
		},
		{
			"name": "tree",
			"posX": 3270,
			"posY": 330,
			"posZ": "over"
		},
		{
			"name": "tree",
			"posX": 3340,
			"posY": 330,
			"posZ": "over"
		},
		{
			"name": "tree",
			"posX": 3410,
			"posY": 330,
			"posZ": "over"
		},
		{
			"name": "tree",
			"posX": 3480,
			"posY": 330,
			"posZ": "over"
		},
		{
			"name": "tree",
			"posX": 3550,
			"posY": 330,
			"posZ": "over"
		},
		{
			"name": "tree",
			"posX": 3620,
			"posY": 330,
			"posZ": "over"
		},
		{
			"name": "tree",
			"posX": 3690,
			"posY": 330,
			"posZ": "over"
		},
		{
			"name": "tree",
			"posX": 3760,
			"posY": 330,
			"posZ": "over"
		},
		{
			"name": "tree",
			"posX": 3830,
			"posY": 330,
			"posZ": "over"
		},
		{
			"name": "tree",
			"posX": 3900,
			"posY": 330,
			"posZ": "over"
		},
		{
			"name": "tree",
			"posX": 3970,
			"posY": 330,
			"posZ": "over"
		},
		{
			"name": "tree",
			"posX": 4040,
			"posY": 330,
			"posZ": "over"
		},
		{
			"name": "tree",
			"posX": 4110,
			"posY": 330,
			"posZ": "over"
		},
		{
			"name": "tree",
			"posX": 4180,
			"posY": 330,
			"posZ": "over"
		},
		{
			"name": "tree",
			"posX": 4250,
			"posY": 330,
			"posZ": "over"
		},
		{
			"name": "tree",
			"posX": 4320,
			"posY": 330,
			"posZ": "over"
		},
		{
			"name": "tree",
			"posX": 4390,
			"posY": 330,
			"posZ": "over"
		},
		{
			"name": "tree",
			"posX": 4460,
			"posY": 330,
			"posZ": "over"
		},
		{
			"name": "tree",
			"posX": 4530,
			"posY": 330,
			"posZ": "over"
		},
		{
			"name": "tree",
			"posX": 4600,
			"posY": 330,
			"posZ": "over"
		},
		{
			"name": "tree",
			"posX": 4670,
			"posY": 330,
			"posZ": "over"
		},
		{
			"name": "tree",
			"posX": 4740,
			"posY": 330,
			"posZ": "over"
		},
		{
			"name": "tree",
			"posX": 4810,
			"posY": 330,
			"posZ": "over"
		},
		{
			"name": "tree",
			"posX": 4880,
			"posY": 330,
			"posZ": "over"
		},
		{
			"name": "tree",
			"posX": 4950,
			"posY": 330,
			"posZ": "over"
		},
		{
			"name": "tree",
			"posX": 5020,
			"posY": 330,
			"posZ": "over"
		},
		{
			"name": "tree",
			"posX": 5090,
			"posY": 330,
			"posZ": "over"
		},
		{
			"name": "tree",
			"posX": 5160,
			"posY": 330,
			"posZ": "over"
		},
		{
			"name": "tree",
			"posX": 5230,
			"posY": 330,
			"posZ": "over"
		},
		{
			"name": "tree",
			"posX": 5300,
			"posY": 330,
			"posZ": "over"
		},
		{
			"name": "tree",
			"posX": 5370,
			"posY": 330,
			"posZ": "over"
		},
		{
			"name": "tree",
			"posX": 5440,
			"posY": 330,
			"posZ": "over"
		},
		{
			"name": "tree",
			"posX": 5510,
			"posY": 330,
			"posZ": "over"
		},
		{
			"name": "tree",
			"posX": 5580,
			"posY": 330,
			"posZ": "over"
		},
		{
			"name": "tree",
			"posX": 5650,
			"posY": 330,
			"posZ": "over"
		},
		{
			"name": "tree",
			"posX": 5720,
			"posY": 330,
			"posZ": "over"
		},
		{
			"name": "tree",
			"posX": 5790,
			"posY": 330,
			"posZ": "over"
		},
		{
			"name": "tree",
			"posX": 5860,
			"posY": 330,
			"posZ": "over"
		},
		{
			"name": "tree",
			"posX": 5930,
			"posY": 330,
			"posZ": "over"
		},
		{
			"name": "tree",
			"posX": 6000,
			"posY": 330,
			"posZ": "over"
		},
		{
			"name": "tree",
			"posX": 6070,
			"posY": 330,
			"posZ": "over"
		},
		{
			"name": "tree",
			"posX": 6140,
			"posY": 330,
			"posZ": "over"
		},
		{
			"name": "tree",
			"posX": 6210,
			"posY": 330,
			"posZ": "over"
		},
		{
			"name": "tree",
			"posX": 6280,
			"posY": 330,
			"posZ": "over"
		},
		{
			"name": "tree",
			"posX": 6350,
			"posY": 330,
			"posZ": "over"
		},
		{
			"name": "tree",
			"posX": 6420,
			"posY": 330,
			"posZ": "over"
		},
		{
			"name": "tree",
			"posX": 6490,
			"posY": 330,
			"posZ": "over"
		},
		{
			"name": "tree",
			"posX": 6560,
			"posY": 330,
			"posZ": "over"
		},
		{
			"name": "tree",
			"posX": 6630,
			"posY": 330,
			"posZ": "over"
		},
		{
			"name": "tree",
			"posX": 6700,
			"posY": 330,
			"posZ": "over"
		},
		{
			"name": "tree",
			"posX": 6770,
			"posY": 330,
			"posZ": "over"
		},
		{
			"name": "tree",
			"posX": 6840,
			"posY": 330,
			"posZ": "over"
		},
		{
			"name": "tree",
			"posX": 6910,
			"posY": 330,
			"posZ": "over"
		},
		{
			"name": "tree",
			"posX": 6980,
			"posY": 330,
			"posZ": "over"
		},
		{
			"name": "tree",
			"posX": 7050,
			"posY": 330,
			"posZ": "over"
		},
		{
			"name": "tree",
			"posX": 85,
			"posY": 400,
			"posZ": "over"
		},
		{
			"name": "tree",
			"posX": 155,
			"posY": 400,
			"posZ": "over"
		},
		{
			"name": "tree",
			"posX": 225,
			"posY": 400,
			"posZ": "over"
		},
		{
			"name": "tree",
			"posX": 295,
			"posY": 400,
			"posZ": "over"
		},
		{
			"name": "tree",
			"posX": 365,
			"posY": 400,
			"posZ": "over"
		},
		{
			"name": "tree",
			"posX": 435,
			"posY": 400,
			"posZ": "over"
		},
		{
			"name": "tree",
			"posX": 505,
			"posY": 400,
			"posZ": "over"
		},
		{
			"name": "tree",
			"posX": 575,
			"posY": 400,
			"posZ": "over"
		},
		{
			"name": "tree",
			"posX": 645,
			"posY": 400,
			"posZ": "over"
		},
		{
			"name": "tree",
			"posX": 715,
			"posY": 400,
			"posZ": "over"
		},
		{
			"name": "tree",
			"posX": 785,
			"posY": 400,
			"posZ": "over"
		},
		{
			"name": "tree",
			"posX": 855,
			"posY": 400,
			"posZ": "over"
		},
		{
			"name": "tree",
			"posX": 925,
			"posY": 400,
			"posZ": "over"
		},
		{
			"name": "tree",
			"posX": 995,
			"posY": 400,
			"posZ": "over"
		},
		{
			"name": "tree",
			"posX": 1065,
			"posY": 400,
			"posZ": "over"
		},
		{
			"name": "tree",
			"posX": 1135,
			"posY": 400,
			"posZ": "over"
		},
		{
			"name": "tree",
			"posX": 1205,
			"posY": 400,
			"posZ": "over"
		},
		{
			"name": "tree",
			"posX": 1275,
			"posY": 400,
			"posZ": "over"
		},
		{
			"name": "tree",
			"posX": 1345,
			"posY": 400,
			"posZ": "over"
		},
		{
			"name": "tree",
			"posX": 1415,
			"posY": 400,
			"posZ": "over"
		},
		{
			"name": "tree",
			"posX": 1485,
			"posY": 400,
			"posZ": "over"
		},
		{
			"name": "tree",
			"posX": 1555,
			"posY": 400,
			"posZ": "over"
		},
		{
			"name": "tree",
			"posX": 1625,
			"posY": 400,
			"posZ": "over"
		},
		{
			"name": "tree",
			"posX": 1695,
			"posY": 400,
			"posZ": "over"
		},
		{
			"name": "tree",
			"posX": 1765,
			"posY": 400,
			"posZ": "over"
		},
		{
			"name": "tree",
			"posX": 1835,
			"posY": 400,
			"posZ": "over"
		},
		{
			"name": "tree",
			"posX": 1905,
			"posY": 400,
			"posZ": "over"
		},
		{
			"name": "tree",
			"posX": 1975,
			"posY": 400,
			"posZ": "over"
		},
		{
			"name": "tree",
			"posX": 2045,
			"posY": 400,
			"posZ": "over"
		},
		{
			"name": "tree",
			"posX": 2115,
			"posY": 400,
			"posZ": "over"
		},
		{
			"name": "tree",
			"posX": 2185,
			"posY": 400,
			"posZ": "over"
		},
		{
			"name": "tree",
			"posX": 2255,
			"posY": 400,
			"posZ": "over"
		},
		{
			"name": "tree",
			"posX": 2325,
			"posY": 400,
			"posZ": "over"
		},
		{
			"name": "tree",
			"posX": 2395,
			"posY": 400,
			"posZ": "over"
		},
		{
			"name": "tree",
			"posX": 2465,
			"posY": 400,
			"posZ": "over"
		},
		{
			"name": "tree",
			"posX": 2535,
			"posY": 400,
			"posZ": "over"
		},
		{
			"name": "tree",
			"posX": 2605,
			"posY": 400,
			"posZ": "over"
		},
		{
			"name": "tree",
			"posX": 2675,
			"posY": 400,
			"posZ": "over"
		},
		{
			"name": "tree",
			"posX": 2745,
			"posY": 400,
			"posZ": "over"
		},
		{
			"name": "tree",
			"posX": 2815,
			"posY": 400,
			"posZ": "over"
		},
		{
			"name": "tree",
			"posX": 2885,
			"posY": 400,
			"posZ": "over"
		},
		{
			"name": "tree",
			"posX": 2955,
			"posY": 400,
			"posZ": "over"
		},
		{
			"name": "tree",
			"posX": 3025,
			"posY": 400,
			"posZ": "over"
		},
		{
			"name": "tree",
			"posX": 3095,
			"posY": 400,
			"posZ": "over"
		},
		{
			"name": "tree",
			"posX": 3165,
			"posY": 400,
			"posZ": "over"
		},
		{
			"name": "tree",
			"posX": 3235,
			"posY": 400,
			"posZ": "over"
		},
		{
			"name": "tree",
			"posX": 3305,
			"posY": 400,
			"posZ": "over"
		},
		{
			"name": "tree",
			"posX": 3375,
			"posY": 400,
			"posZ": "over"
		},
		{
			"name": "tree",
			"posX": 3445,
			"posY": 400,
			"posZ": "over"
		},
		{
			"name": "tree",
			"posX": 3515,
			"posY": 400,
			"posZ": "over"
		},
		{
			"name": "tree",
			"posX": 3585,
			"posY": 400,
			"posZ": "over"
		},
		{
			"name": "tree",
			"posX": 3655,
			"posY": 400,
			"posZ": "over"
		},
		{
			"name": "tree",
			"posX": 3725,
			"posY": 400,
			"posZ": "over"
		},
		{
			"name": "tree",
			"posX": 3795,
			"posY": 400,
			"posZ": "over"
		},
		{
			"name": "tree",
			"posX": 3865,
			"posY": 400,
			"posZ": "over"
		},
		{
			"name": "tree",
			"posX": 3935,
			"posY": 400,
			"posZ": "over"
		},
		{
			"name": "tree",
			"posX": 4005,
			"posY": 400,
			"posZ": "over"
		},
		{
			"name": "tree",
			"posX": 4075,
			"posY": 400,
			"posZ": "over"
		},
		{
			"name": "tree",
			"posX": 4145,
			"posY": 400,
			"posZ": "over"
		},
		{
			"name": "tree",
			"posX": 4215,
			"posY": 400,
			"posZ": "over"
		},
		{
			"name": "tree",
			"posX": 4285,
			"posY": 400,
			"posZ": "over"
		},
		{
			"name": "tree",
			"posX": 4355,
			"posY": 400,
			"posZ": "over"
		},
		{
			"name": "tree",
			"posX": 4425,
			"posY": 400,
			"posZ": "over"
		},
		{
			"name": "tree",
			"posX": 4495,
			"posY": 400,
			"posZ": "over"
		},
		{
			"name": "tree",
			"posX": 4565,
			"posY": 400,
			"posZ": "over"
		},
		{
			"name": "tree",
			"posX": 4635,
			"posY": 400,
			"posZ": "over"
		},
		{
			"name": "tree",
			"posX": 4705,
			"posY": 400,
			"posZ": "over"
		},
		{
			"name": "tree",
			"posX": 4775,
			"posY": 400,
			"posZ": "over"
		},
		{
			"name": "tree",
			"posX": 4845,
			"posY": 400,
			"posZ": "over"
		},
		{
			"name": "tree",
			"posX": 4915,
			"posY": 400,
			"posZ": "over"
		},
		{
			"name": "tree",
			"posX": 4985,
			"posY": 400,
			"posZ": "over"
		},
		{
			"name": "tree",
			"posX": 5055,
			"posY": 400,
			"posZ": "over"
		},
		{
			"name": "tree",
			"posX": 5125,
			"posY": 400,
			"posZ": "over"
		},
		{
			"name": "tree",
			"posX": 5195,
			"posY": 400,
			"posZ": "over"
		},
		{
			"name": "tree",
			"posX": 5265,
			"posY": 400,
			"posZ": "over"
		},
		{
			"name": "tree",
			"posX": 5335,
			"posY": 400,
			"posZ": "over"
		},
		{
			"name": "tree",
			"posX": 5405,
			"posY": 400,
			"posZ": "over"
		},
		{
			"name": "tree",
			"posX": 5475,
			"posY": 400,
			"posZ": "over"
		},
		{
			"name": "tree",
			"posX": 5545,
			"posY": 400,
			"posZ": "over"
		},
		{
			"name": "tree",
			"posX": 5615,
			"posY": 400,
			"posZ": "over"
		},
		{
			"name": "tree",
			"posX": 5685,
			"posY": 400,
			"posZ": "over"
		},
		{
			"name": "tree",
			"posX": 5755,
			"posY": 400,
			"posZ": "over"
		},
		{
			"name": "tree",
			"posX": 5825,
			"posY": 400,
			"posZ": "over"
		},
		{
			"name": "tree",
			"posX": 5895,
			"posY": 400,
			"posZ": "over"
		},
		{
			"name": "tree",
			"posX": 5965,
			"posY": 400,
			"posZ": "over"
		},
		{
			"name": "tree",
			"posX": 6035,
			"posY": 400,
			"posZ": "over"
		},
		{
			"name": "tree",
			"posX": 6105,
			"posY": 400,
			"posZ": "over"
		},
		{
			"name": "tree",
			"posX": 6175,
			"posY": 400,
			"posZ": "over"
		},
		{
			"name": "tree",
			"posX": 6245,
			"posY": 400,
			"posZ": "over"
		},
		{
			"name": "tree",
			"posX": 6315,
			"posY": 400,
			"posZ": "over"
		},
		{
			"name": "tree",
			"posX": 6385,
			"posY": 400,
			"posZ": "over"
		},
		{
			"name": "tree",
			"posX": 6455,
			"posY": 400,
			"posZ": "over"
		},
		{
			"name": "tree",
			"posX": 6525,
			"posY": 400,
			"posZ": "over"
		},
		{
			"name": "tree",
			"posX": 6595,
			"posY": 400,
			"posZ": "over"
		},
		{
			"name": "tree",
			"posX": 6665,
			"posY": 400,
			"posZ": "over"
		},
		{
			"name": "tree",
			"posX": 6735,
			"posY": 400,
			"posZ": "over"
		},
		{
			"name": "tree",
			"posX": 6805,
			"posY": 400,
			"posZ": "over"
		},
		{
			"name": "tree",
			"posX": 6875,
			"posY": 400,
			"posZ": "over"
		},
		{
			"name": "tree",
			"posX": 6945,
			"posY": 400,
			"posZ": "over"
		},
		{
			"name": "tree",
			"posX": 7015,
			"posY": 400,
			"posZ": "over"
		},
		{
			"name": "tree",
			"posX": 50,
			"posY": 470,
			"posZ": "over"
		},
		{
			"name": "tree",
			"posX": 120,
			"posY": 470,
			"posZ": "over"
		},
		{
			"name": "tree",
			"posX": 190,
			"posY": 470,
			"posZ": "over"
		},
		{
			"name": "tree",
			"posX": 260,
			"posY": 470,
			"posZ": "over"
		},
		{
			"name": "tree",
			"posX": 330,
			"posY": 470,
			"posZ": "over"
		},
		{
			"name": "tree",
			"posX": 400,
			"posY": 470,
			"posZ": "over"
		},
		{
			"name": "tree",
			"posX": 470,
			"posY": 470,
			"posZ": "over"
		},
		{
			"name": "tree",
			"posX": 540,
			"posY": 470,
			"posZ": "over"
		},
		{
			"name": "tree",
			"posX": 610,
			"posY": 470,
			"posZ": "over"
		},
		{
			"name": "tree",
			"posX": 680,
			"posY": 470,
			"posZ": "over"
		},
		{
			"name": "tree",
			"posX": 750,
			"posY": 470,
			"posZ": "over"
		},
		{
			"name": "tree",
			"posX": 820,
			"posY": 470,
			"posZ": "over"
		},
		{
			"name": "tree",
			"posX": 890,
			"posY": 470,
			"posZ": "over"
		},
		{
			"name": "tree",
			"posX": 960,
			"posY": 470,
			"posZ": "over"
		},
		{
			"name": "tree",
			"posX": 1030,
			"posY": 470,
			"posZ": "over"
		},
		{
			"name": "tree",
			"posX": 1100,
			"posY": 470,
			"posZ": "over"
		},
		{
			"name": "tree",
			"posX": 1170,
			"posY": 470,
			"posZ": "over"
		},
		{
			"name": "tree",
			"posX": 1240,
			"posY": 470,
			"posZ": "over"
		},
		{
			"name": "tree",
			"posX": 1310,
			"posY": 470,
			"posZ": "over"
		},
		{
			"name": "tree",
			"posX": 1380,
			"posY": 470,
			"posZ": "over"
		},
		{
			"name": "tree",
			"posX": 1450,
			"posY": 470,
			"posZ": "over"
		},
		{
			"name": "tree",
			"posX": 1520,
			"posY": 470,
			"posZ": "over"
		},
		{
			"name": "tree",
			"posX": 1590,
			"posY": 470,
			"posZ": "over"
		},
		{
			"name": "tree",
			"posX": 1660,
			"posY": 470,
			"posZ": "over"
		},
		{
			"name": "tree",
			"posX": 1730,
			"posY": 470,
			"posZ": "over"
		},
		{
			"name": "tree",
			"posX": 1800,
			"posY": 470,
			"posZ": "over"
		},
		{
			"name": "tree",
			"posX": 1870,
			"posY": 470,
			"posZ": "over"
		},
		{
			"name": "tree",
			"posX": 1940,
			"posY": 470,
			"posZ": "over"
		},
		{
			"name": "tree",
			"posX": 2010,
			"posY": 470,
			"posZ": "over"
		},
		{
			"name": "tree",
			"posX": 2080,
			"posY": 470,
			"posZ": "over"
		},
		{
			"name": "tree",
			"posX": 2150,
			"posY": 470,
			"posZ": "over"
		},
		{
			"name": "tree",
			"posX": 2220,
			"posY": 470,
			"posZ": "over"
		},
		{
			"name": "tree",
			"posX": 2290,
			"posY": 470,
			"posZ": "over"
		},
		{
			"name": "tree",
			"posX": 2360,
			"posY": 470,
			"posZ": "over"
		},
		{
			"name": "tree",
			"posX": 2430,
			"posY": 470,
			"posZ": "over"
		},
		{
			"name": "tree",
			"posX": 2500,
			"posY": 470,
			"posZ": "over"
		},
		{
			"name": "tree",
			"posX": 2570,
			"posY": 470,
			"posZ": "over"
		},
		{
			"name": "tree",
			"posX": 2640,
			"posY": 470,
			"posZ": "over"
		},
		{
			"name": "tree",
			"posX": 2710,
			"posY": 470,
			"posZ": "over"
		},
		{
			"name": "tree",
			"posX": 2780,
			"posY": 470,
			"posZ": "over"
		},
		{
			"name": "tree",
			"posX": 2850,
			"posY": 470,
			"posZ": "over"
		},
		{
			"name": "tree",
			"posX": 2920,
			"posY": 470,
			"posZ": "over"
		},
		{
			"name": "tree",
			"posX": 2990,
			"posY": 470,
			"posZ": "over"
		},
		{
			"name": "tree",
			"posX": 3060,
			"posY": 470,
			"posZ": "over"
		},
		{
			"name": "tree",
			"posX": 3130,
			"posY": 470,
			"posZ": "over"
		},
		{
			"name": "tree",
			"posX": 3200,
			"posY": 470,
			"posZ": "over"
		},
		{
			"name": "tree",
			"posX": 3270,
			"posY": 470,
			"posZ": "over"
		},
		{
			"name": "tree",
			"posX": 3340,
			"posY": 470,
			"posZ": "over"
		},
		{
			"name": "tree",
			"posX": 3410,
			"posY": 470,
			"posZ": "over"
		},
		{
			"name": "tree",
			"posX": 3480,
			"posY": 470,
			"posZ": "over"
		},
		{
			"name": "tree",
			"posX": 3550,
			"posY": 470,
			"posZ": "over"
		},
		{
			"name": "tree",
			"posX": 3620,
			"posY": 470,
			"posZ": "over"
		},
		{
			"name": "tree",
			"posX": 3690,
			"posY": 470,
			"posZ": "over"
		},
		{
			"name": "tree",
			"posX": 3760,
			"posY": 470,
			"posZ": "over"
		},
		{
			"name": "tree",
			"posX": 3830,
			"posY": 470,
			"posZ": "over"
		},
		{
			"name": "tree",
			"posX": 3900,
			"posY": 470,
			"posZ": "over"
		},
		{
			"name": "tree",
			"posX": 3970,
			"posY": 470,
			"posZ": "over"
		},
		{
			"name": "tree",
			"posX": 4040,
			"posY": 470,
			"posZ": "over"
		},
		{
			"name": "tree",
			"posX": 4110,
			"posY": 470,
			"posZ": "over"
		},
		{
			"name": "tree",
			"posX": 4180,
			"posY": 470,
			"posZ": "over"
		},
		{
			"name": "tree",
			"posX": 4250,
			"posY": 470,
			"posZ": "over"
		},
		{
			"name": "tree",
			"posX": 4320,
			"posY": 470,
			"posZ": "over"
		},
		{
			"name": "tree",
			"posX": 4390,
			"posY": 470,
			"posZ": "over"
		},
		{
			"name": "tree",
			"posX": 4460,
			"posY": 470,
			"posZ": "over"
		},
		{
			"name": "tree",
			"posX": 4530,
			"posY": 470,
			"posZ": "over"
		},
		{
			"name": "tree",
			"posX": 4600,
			"posY": 470,
			"posZ": "over"
		},
		{
			"name": "tree",
			"posX": 4670,
			"posY": 470,
			"posZ": "over"
		},
		{
			"name": "tree",
			"posX": 4740,
			"posY": 470,
			"posZ": "over"
		},
		{
			"name": "tree",
			"posX": 4810,
			"posY": 470,
			"posZ": "over"
		},
		{
			"name": "tree",
			"posX": 4880,
			"posY": 470,
			"posZ": "over"
		},
		{
			"name": "tree",
			"posX": 4950,
			"posY": 470,
			"posZ": "over"
		},
		{
			"name": "tree",
			"posX": 5020,
			"posY": 470,
			"posZ": "over"
		},
		{
			"name": "tree",
			"posX": 5090,
			"posY": 470,
			"posZ": "over"
		},
		{
			"name": "tree",
			"posX": 5160,
			"posY": 470,
			"posZ": "over"
		},
		{
			"name": "tree",
			"posX": 5230,
			"posY": 470,
			"posZ": "over"
		},
		{
			"name": "tree",
			"posX": 5300,
			"posY": 470,
			"posZ": "over"
		},
		{
			"name": "tree",
			"posX": 5370,
			"posY": 470,
			"posZ": "over"
		},
		{
			"name": "tree",
			"posX": 5440,
			"posY": 470,
			"posZ": "over"
		},
		{
			"name": "tree",
			"posX": 5510,
			"posY": 470,
			"posZ": "over"
		},
		{
			"name": "tree",
			"posX": 5580,
			"posY": 470,
			"posZ": "over"
		},
		{
			"name": "tree",
			"posX": 5650,
			"posY": 470,
			"posZ": "over"
		},
		{
			"name": "tree",
			"posX": 5720,
			"posY": 470,
			"posZ": "over"
		},
		{
			"name": "tree",
			"posX": 5790,
			"posY": 470,
			"posZ": "over"
		},
		{
			"name": "tree",
			"posX": 5860,
			"posY": 470,
			"posZ": "over"
		},
		{
			"name": "tree",
			"posX": 5930,
			"posY": 470,
			"posZ": "over"
		},
		{
			"name": "tree",
			"posX": 6000,
			"posY": 470,
			"posZ": "over"
		},
		{
			"name": "tree",
			"posX": 6070,
			"posY": 470,
			"posZ": "over"
		},
		{
			"name": "tree",
			"posX": 6140,
			"posY": 470,
			"posZ": "over"
		},
		{
			"name": "tree",
			"posX": 6210,
			"posY": 470,
			"posZ": "over"
		},
		{
			"name": "tree",
			"posX": 6280,
			"posY": 470,
			"posZ": "over"
		},
		{
			"name": "tree",
			"posX": 6350,
			"posY": 470,
			"posZ": "over"
		},
		{
			"name": "tree",
			"posX": 6420,
			"posY": 470,
			"posZ": "over"
		},
		{
			"name": "tree",
			"posX": 6490,
			"posY": 470,
			"posZ": "over"
		},
		{
			"name": "tree",
			"posX": 6560,
			"posY": 470,
			"posZ": "over"
		},
		{
			"name": "tree",
			"posX": 6630,
			"posY": 470,
			"posZ": "over"
		},
		{
			"name": "tree",
			"posX": 6700,
			"posY": 470,
			"posZ": "over"
		},
		{
			"name": "tree",
			"posX": 6770,
			"posY": 470,
			"posZ": "over"
		},
		{
			"name": "tree",
			"posX": 6840,
			"posY": 470,
			"posZ": "over"
		},
		{
			"name": "tree",
			"posX": 6910,
			"posY": 470,
			"posZ": "over"
		},
		{
			"name": "tree",
			"posX": 6980,
			"posY": 470,
			"posZ": "over"
		},
		{
			"name": "tree",
			"posX": 7050,
			"posY": 470,
			"posZ": "over"
		},
		{
			"name": "tree",
			"posX": 85,
			"posY": 540,
			"posZ": "over"
		},
		{
			"name": "tree",
			"posX": 155,
			"posY": 540,
			"posZ": "over"
		},
		{
			"name": "tree",
			"posX": 225,
			"posY": 540,
			"posZ": "over"
		},
		{
			"name": "tree",
			"posX": 295,
			"posY": 540,
			"posZ": "over"
		},
		{
			"name": "tree",
			"posX": 365,
			"posY": 540,
			"posZ": "over"
		},
		{
			"name": "tree",
			"posX": 435,
			"posY": 540,
			"posZ": "over"
		},
		{
			"name": "tree",
			"posX": 505,
			"posY": 540,
			"posZ": "over"
		},
		{
			"name": "tree",
			"posX": 575,
			"posY": 540,
			"posZ": "over"
		},
		{
			"name": "tree",
			"posX": 645,
			"posY": 540,
			"posZ": "over"
		},
		{
			"name": "tree",
			"posX": 715,
			"posY": 540,
			"posZ": "over"
		},
		{
			"name": "tree",
			"posX": 785,
			"posY": 540,
			"posZ": "over"
		},
		{
			"name": "tree",
			"posX": 855,
			"posY": 540,
			"posZ": "over"
		},
		{
			"name": "tree",
			"posX": 925,
			"posY": 540,
			"posZ": "over"
		},
		{
			"name": "tree",
			"posX": 995,
			"posY": 540,
			"posZ": "over"
		},
		{
			"name": "tree",
			"posX": 1065,
			"posY": 540,
			"posZ": "over"
		},
		{
			"name": "tree",
			"posX": 1135,
			"posY": 540,
			"posZ": "over"
		},
		{
			"name": "tree",
			"posX": 1205,
			"posY": 540,
			"posZ": "over"
		},
		{
			"name": "tree",
			"posX": 1275,
			"posY": 540,
			"posZ": "over"
		},
		{
			"name": "tree",
			"posX": 1345,
			"posY": 540,
			"posZ": "over"
		},
		{
			"name": "tree",
			"posX": 1415,
			"posY": 540,
			"posZ": "over"
		},
		{
			"name": "tree",
			"posX": 1485,
			"posY": 540,
			"posZ": "over"
		},
		{
			"name": "tree",
			"posX": 1555,
			"posY": 540,
			"posZ": "over"
		},
		{
			"name": "tree",
			"posX": 1625,
			"posY": 540,
			"posZ": "over"
		},
		{
			"name": "tree",
			"posX": 1695,
			"posY": 540,
			"posZ": "over"
		},
		{
			"name": "tree",
			"posX": 1765,
			"posY": 540,
			"posZ": "over"
		},
		{
			"name": "tree",
			"posX": 1835,
			"posY": 540,
			"posZ": "over"
		},
		{
			"name": "tree",
			"posX": 1905,
			"posY": 540,
			"posZ": "over"
		},
		{
			"name": "tree",
			"posX": 1975,
			"posY": 540,
			"posZ": "over"
		},
		{
			"name": "tree",
			"posX": 2045,
			"posY": 540,
			"posZ": "over"
		},
		{
			"name": "tree",
			"posX": 2115,
			"posY": 540,
			"posZ": "over"
		},
		{
			"name": "tree",
			"posX": 2185,
			"posY": 540,
			"posZ": "over"
		},
		{
			"name": "tree",
			"posX": 2255,
			"posY": 540,
			"posZ": "over"
		},
		{
			"name": "tree",
			"posX": 2325,
			"posY": 540,
			"posZ": "over"
		},
		{
			"name": "tree",
			"posX": 2395,
			"posY": 540,
			"posZ": "over"
		},
		{
			"name": "tree",
			"posX": 2465,
			"posY": 540,
			"posZ": "over"
		},
		{
			"name": "tree",
			"posX": 2535,
			"posY": 540,
			"posZ": "over"
		},
		{
			"name": "tree",
			"posX": 2605,
			"posY": 540,
			"posZ": "over"
		},
		{
			"name": "tree",
			"posX": 2675,
			"posY": 540,
			"posZ": "over"
		},
		{
			"name": "tree",
			"posX": 2745,
			"posY": 540,
			"posZ": "over"
		},
		{
			"name": "tree",
			"posX": 2815,
			"posY": 540,
			"posZ": "over"
		},
		{
			"name": "tree",
			"posX": 2885,
			"posY": 540,
			"posZ": "over"
		},
		{
			"name": "tree",
			"posX": 2955,
			"posY": 540,
			"posZ": "over"
		},
		{
			"name": "tree",
			"posX": 3025,
			"posY": 540,
			"posZ": "over"
		},
		{
			"name": "tree",
			"posX": 3095,
			"posY": 540,
			"posZ": "over"
		},
		{
			"name": "tree",
			"posX": 3165,
			"posY": 540,
			"posZ": "over"
		},
		{
			"name": "tree",
			"posX": 3235,
			"posY": 540,
			"posZ": "over"
		},
		{
			"name": "tree",
			"posX": 3305,
			"posY": 540,
			"posZ": "over"
		},
		{
			"name": "tree",
			"posX": 3375,
			"posY": 540,
			"posZ": "over"
		},
		{
			"name": "tree",
			"posX": 3445,
			"posY": 540,
			"posZ": "over"
		},
		{
			"name": "tree",
			"posX": 3515,
			"posY": 540,
			"posZ": "over"
		},
		{
			"name": "tree",
			"posX": 3585,
			"posY": 540,
			"posZ": "over"
		},
		{
			"name": "tree",
			"posX": 3655,
			"posY": 540,
			"posZ": "over"
		},
		{
			"name": "tree",
			"posX": 3725,
			"posY": 540,
			"posZ": "over"
		},
		{
			"name": "tree",
			"posX": 3795,
			"posY": 540,
			"posZ": "over"
		},
		{
			"name": "tree",
			"posX": 3865,
			"posY": 540,
			"posZ": "over"
		},
		{
			"name": "tree",
			"posX": 3935,
			"posY": 540,
			"posZ": "over"
		},
		{
			"name": "tree",
			"posX": 4005,
			"posY": 540,
			"posZ": "over"
		},
		{
			"name": "tree",
			"posX": 4075,
			"posY": 540,
			"posZ": "over"
		},
		{
			"name": "tree",
			"posX": 4145,
			"posY": 540,
			"posZ": "over"
		},
		{
			"name": "tree",
			"posX": 4215,
			"posY": 540,
			"posZ": "over"
		},
		{
			"name": "tree",
			"posX": 4285,
			"posY": 540,
			"posZ": "over"
		},
		{
			"name": "tree",
			"posX": 4355,
			"posY": 540,
			"posZ": "over"
		},
		{
			"name": "tree",
			"posX": 4425,
			"posY": 540,
			"posZ": "over"
		},
		{
			"name": "tree",
			"posX": 4495,
			"posY": 540,
			"posZ": "over"
		},
		{
			"name": "tree",
			"posX": 4565,
			"posY": 540,
			"posZ": "over"
		},
		{
			"name": "tree",
			"posX": 4635,
			"posY": 540,
			"posZ": "over"
		},
		{
			"name": "tree",
			"posX": 4705,
			"posY": 540,
			"posZ": "over"
		},
		{
			"name": "tree",
			"posX": 4775,
			"posY": 540,
			"posZ": "over"
		},
		{
			"name": "tree",
			"posX": 4845,
			"posY": 540,
			"posZ": "over"
		},
		{
			"name": "tree",
			"posX": 4915,
			"posY": 540,
			"posZ": "over"
		},
		{
			"name": "tree",
			"posX": 4985,
			"posY": 540,
			"posZ": "over"
		},
		{
			"name": "tree",
			"posX": 5055,
			"posY": 540,
			"posZ": "over"
		},
		{
			"name": "tree",
			"posX": 5125,
			"posY": 540,
			"posZ": "over"
		},
		{
			"name": "tree",
			"posX": 5195,
			"posY": 540,
			"posZ": "over"
		},
		{
			"name": "tree",
			"posX": 5265,
			"posY": 540,
			"posZ": "over"
		},
		{
			"name": "tree",
			"posX": 5335,
			"posY": 540,
			"posZ": "over"
		},
		{
			"name": "tree",
			"posX": 5405,
			"posY": 540,
			"posZ": "over"
		},
		{
			"name": "tree",
			"posX": 5475,
			"posY": 540,
			"posZ": "over"
		},
		{
			"name": "tree",
			"posX": 5545,
			"posY": 540,
			"posZ": "over"
		},
		{
			"name": "tree",
			"posX": 5615,
			"posY": 540,
			"posZ": "over"
		},
		{
			"name": "tree",
			"posX": 5685,
			"posY": 540,
			"posZ": "over"
		},
		{
			"name": "tree",
			"posX": 5755,
			"posY": 540,
			"posZ": "over"
		},
		{
			"name": "tree",
			"posX": 5825,
			"posY": 540,
			"posZ": "over"
		},
		{
			"name": "tree",
			"posX": 5895,
			"posY": 540,
			"posZ": "over"
		},
		{
			"name": "tree",
			"posX": 5965,
			"posY": 540,
			"posZ": "over"
		},
		{
			"name": "tree",
			"posX": 6035,
			"posY": 540,
			"posZ": "over"
		},
		{
			"name": "tree",
			"posX": 6105,
			"posY": 540,
			"posZ": "over"
		},
		{
			"name": "tree",
			"posX": 6175,
			"posY": 540,
			"posZ": "over"
		},
		{
			"name": "tree",
			"posX": 6245,
			"posY": 540,
			"posZ": "over"
		},
		{
			"name": "tree",
			"posX": 6315,
			"posY": 540,
			"posZ": "over"
		},
		{
			"name": "tree",
			"posX": 6385,
			"posY": 540,
			"posZ": "over"
		},
		{
			"name": "tree",
			"posX": 6455,
			"posY": 540,
			"posZ": "over"
		},
		{
			"name": "tree",
			"posX": 6525,
			"posY": 540,
			"posZ": "over"
		},
		{
			"name": "tree",
			"posX": 6595,
			"posY": 540,
			"posZ": "over"
		},
		{
			"name": "tree",
			"posX": 6665,
			"posY": 540,
			"posZ": "over"
		},
		{
			"name": "tree",
			"posX": 6735,
			"posY": 540,
			"posZ": "over"
		},
		{
			"name": "tree",
			"posX": 6805,
			"posY": 540,
			"posZ": "over"
		},
		{
			"name": "tree",
			"posX": 6875,
			"posY": 540,
			"posZ": "over"
		},
		{
			"name": "tree",
			"posX": 6945,
			"posY": 540,
			"posZ": "over"
		},
		{
			"name": "tree",
			"posX": 7015,
			"posY": 540,
			"posZ": "over"
		},
		{
			"name": "tree",
			"posX": 50,
			"posY": 610,
			"posZ": "over"
		},
		{
			"name": "tree",
			"posX": 120,
			"posY": 610,
			"posZ": "over"
		},
		{
			"name": "tree",
			"posX": 190,
			"posY": 610,
			"posZ": "over"
		},
		{
			"name": "tree",
			"posX": 260,
			"posY": 610,
			"posZ": "over"
		},
		{
			"name": "tree",
			"posX": 330,
			"posY": 610,
			"posZ": "over"
		},
		{
			"name": "tree",
			"posX": 400,
			"posY": 610,
			"posZ": "over"
		},
		{
			"name": "tree",
			"posX": 470,
			"posY": 610,
			"posZ": "over"
		},
		{
			"name": "tree",
			"posX": 540,
			"posY": 610,
			"posZ": "over"
		},
		{
			"name": "tree",
			"posX": 610,
			"posY": 610,
			"posZ": "over"
		},
		{
			"name": "tree",
			"posX": 680,
			"posY": 610,
			"posZ": "over"
		},
		{
			"name": "tree",
			"posX": 750,
			"posY": 610,
			"posZ": "over"
		},
		{
			"name": "tree",
			"posX": 820,
			"posY": 610,
			"posZ": "over"
		},
		{
			"name": "tree",
			"posX": 890,
			"posY": 610,
			"posZ": "over"
		},
		{
			"name": "tree",
			"posX": 960,
			"posY": 610,
			"posZ": "over"
		},
		{
			"name": "tree",
			"posX": 1030,
			"posY": 610,
			"posZ": "over"
		},
		{
			"name": "tree",
			"posX": 1100,
			"posY": 610,
			"posZ": "over"
		},
		{
			"name": "tree",
			"posX": 1170,
			"posY": 610,
			"posZ": "over"
		},
		{
			"name": "tree",
			"posX": 1240,
			"posY": 610,
			"posZ": "over"
		},
		{
			"name": "tree",
			"posX": 1310,
			"posY": 610,
			"posZ": "over"
		},
		{
			"name": "tree",
			"posX": 1380,
			"posY": 610,
			"posZ": "over"
		},
		{
			"name": "tree",
			"posX": 1450,
			"posY": 610,
			"posZ": "over"
		},
		{
			"name": "tree",
			"posX": 1520,
			"posY": 610,
			"posZ": "over"
		},
		{
			"name": "tree",
			"posX": 1590,
			"posY": 610,
			"posZ": "over"
		},
		{
			"name": "tree",
			"posX": 1660,
			"posY": 610,
			"posZ": "over"
		},
		{
			"name": "tree",
			"posX": 1730,
			"posY": 610,
			"posZ": "over"
		},
		{
			"name": "tree",
			"posX": 1800,
			"posY": 610,
			"posZ": "over"
		},
		{
			"name": "tree",
			"posX": 1870,
			"posY": 610,
			"posZ": "over"
		},
		{
			"name": "tree",
			"posX": 1940,
			"posY": 610,
			"posZ": "over"
		},
		{
			"name": "tree",
			"posX": 2010,
			"posY": 610,
			"posZ": "over"
		},
		{
			"name": "tree",
			"posX": 2080,
			"posY": 610,
			"posZ": "over"
		},
		{
			"name": "tree",
			"posX": 2150,
			"posY": 610,
			"posZ": "over"
		},
		{
			"name": "tree",
			"posX": 2220,
			"posY": 610,
			"posZ": "over"
		},
		{
			"name": "tree",
			"posX": 2290,
			"posY": 610,
			"posZ": "over"
		},
		{
			"name": "tree",
			"posX": 2360,
			"posY": 610,
			"posZ": "over"
		},
		{
			"name": "tree",
			"posX": 2430,
			"posY": 610,
			"posZ": "over"
		},
		{
			"name": "tree",
			"posX": 2500,
			"posY": 610,
			"posZ": "over"
		},
		{
			"name": "tree",
			"posX": 2570,
			"posY": 610,
			"posZ": "over"
		},
		{
			"name": "tree",
			"posX": 2640,
			"posY": 610,
			"posZ": "over"
		},
		{
			"name": "tree",
			"posX": 2710,
			"posY": 610,
			"posZ": "over"
		},
		{
			"name": "tree",
			"posX": 2780,
			"posY": 610,
			"posZ": "over"
		},
		{
			"name": "tree",
			"posX": 2850,
			"posY": 610,
			"posZ": "over"
		},
		{
			"name": "tree",
			"posX": 2920,
			"posY": 610,
			"posZ": "over"
		},
		{
			"name": "tree",
			"posX": 2990,
			"posY": 610,
			"posZ": "over"
		},
		{
			"name": "tree",
			"posX": 3060,
			"posY": 610,
			"posZ": "over"
		},
		{
			"name": "tree",
			"posX": 3130,
			"posY": 610,
			"posZ": "over"
		},
		{
			"name": "tree",
			"posX": 3200,
			"posY": 610,
			"posZ": "over"
		},
		{
			"name": "tree",
			"posX": 3270,
			"posY": 610,
			"posZ": "over"
		},
		{
			"name": "tree",
			"posX": 3340,
			"posY": 610,
			"posZ": "over"
		},
		{
			"name": "tree",
			"posX": 3410,
			"posY": 610,
			"posZ": "over"
		},
		{
			"name": "tree",
			"posX": 3480,
			"posY": 610,
			"posZ": "over"
		},
		{
			"name": "tree",
			"posX": 3550,
			"posY": 610,
			"posZ": "over"
		},
		{
			"name": "tree",
			"posX": 3620,
			"posY": 610,
			"posZ": "over"
		},
		{
			"name": "tree",
			"posX": 3690,
			"posY": 610,
			"posZ": "over"
		},
		{
			"name": "tree",
			"posX": 3760,
			"posY": 610,
			"posZ": "over"
		},
		{
			"name": "tree",
			"posX": 3830,
			"posY": 610,
			"posZ": "over"
		},
		{
			"name": "tree",
			"posX": 3900,
			"posY": 610,
			"posZ": "over"
		},
		{
			"name": "tree",
			"posX": 3970,
			"posY": 610,
			"posZ": "over"
		},
		{
			"name": "tree",
			"posX": 4040,
			"posY": 610,
			"posZ": "over"
		},
		{
			"name": "tree",
			"posX": 4110,
			"posY": 610,
			"posZ": "over"
		},
		{
			"name": "tree",
			"posX": 4180,
			"posY": 610,
			"posZ": "over"
		},
		{
			"name": "tree",
			"posX": 4250,
			"posY": 610,
			"posZ": "over"
		},
		{
			"name": "tree",
			"posX": 4320,
			"posY": 610,
			"posZ": "over"
		},
		{
			"name": "tree",
			"posX": 4390,
			"posY": 610,
			"posZ": "over"
		},
		{
			"name": "tree",
			"posX": 4460,
			"posY": 610,
			"posZ": "over"
		},
		{
			"name": "tree",
			"posX": 4530,
			"posY": 610,
			"posZ": "over"
		},
		{
			"name": "tree",
			"posX": 4600,
			"posY": 610,
			"posZ": "over"
		},
		{
			"name": "tree",
			"posX": 4670,
			"posY": 610,
			"posZ": "over"
		},
		{
			"name": "tree",
			"posX": 4740,
			"posY": 610,
			"posZ": "over"
		},
		{
			"name": "tree",
			"posX": 4810,
			"posY": 610,
			"posZ": "over"
		},
		{
			"name": "tree",
			"posX": 4880,
			"posY": 610,
			"posZ": "over"
		},
		{
			"name": "tree",
			"posX": 4950,
			"posY": 610,
			"posZ": "over"
		},
		{
			"name": "tree",
			"posX": 5020,
			"posY": 610,
			"posZ": "over"
		},
		{
			"name": "tree",
			"posX": 5090,
			"posY": 610,
			"posZ": "over"
		},
		{
			"name": "tree",
			"posX": 5160,
			"posY": 610,
			"posZ": "over"
		},
		{
			"name": "tree",
			"posX": 5230,
			"posY": 610,
			"posZ": "over"
		},
		{
			"name": "tree",
			"posX": 5300,
			"posY": 610,
			"posZ": "over"
		},
		{
			"name": "tree",
			"posX": 5370,
			"posY": 610,
			"posZ": "over"
		},
		{
			"name": "tree",
			"posX": 5440,
			"posY": 610,
			"posZ": "over"
		},
		{
			"name": "tree",
			"posX": 5510,
			"posY": 610,
			"posZ": "over"
		},
		{
			"name": "tree",
			"posX": 5580,
			"posY": 610,
			"posZ": "over"
		},
		{
			"name": "tree",
			"posX": 5650,
			"posY": 610,
			"posZ": "over"
		},
		{
			"name": "tree",
			"posX": 5720,
			"posY": 610,
			"posZ": "over"
		},
		{
			"name": "tree",
			"posX": 5790,
			"posY": 610,
			"posZ": "over"
		},
		{
			"name": "tree",
			"posX": 5860,
			"posY": 610,
			"posZ": "over"
		},
		{
			"name": "tree",
			"posX": 5930,
			"posY": 610,
			"posZ": "over"
		},
		{
			"name": "tree",
			"posX": 6000,
			"posY": 610,
			"posZ": "over"
		},
		{
			"name": "tree",
			"posX": 6070,
			"posY": 610,
			"posZ": "over"
		},
		{
			"name": "tree",
			"posX": 6140,
			"posY": 610,
			"posZ": "over"
		},
		{
			"name": "tree",
			"posX": 6210,
			"posY": 610,
			"posZ": "over"
		},
		{
			"name": "tree",
			"posX": 6280,
			"posY": 610,
			"posZ": "over"
		},
		{
			"name": "tree",
			"posX": 6350,
			"posY": 610,
			"posZ": "over"
		},
		{
			"name": "tree",
			"posX": 6420,
			"posY": 610,
			"posZ": "over"
		},
		{
			"name": "tree",
			"posX": 6490,
			"posY": 610,
			"posZ": "over"
		},
		{
			"name": "tree",
			"posX": 6560,
			"posY": 610,
			"posZ": "over"
		},
		{
			"name": "tree",
			"posX": 6630,
			"posY": 610,
			"posZ": "over"
		},
		{
			"name": "tree",
			"posX": 6700,
			"posY": 610,
			"posZ": "over"
		},
		{
			"name": "tree",
			"posX": 6770,
			"posY": 610,
			"posZ": "over"
		},
		{
			"name": "tree",
			"posX": 6840,
			"posY": 610,
			"posZ": "over"
		},
		{
			"name": "tree",
			"posX": 6910,
			"posY": 610,
			"posZ": "over"
		},
		{
			"name": "tree",
			"posX": 6980,
			"posY": 610,
			"posZ": "over"
		},
		{
			"name": "tree",
			"posX": 7050,
			"posY": 610,
			"posZ": "over"
		},
		{
			"name": "tree",
			"posX": 85,
			"posY": 680,
			"posZ": "over"
		},
		{
			"name": "tree",
			"posX": 155,
			"posY": 680,
			"posZ": "over"
		},
		{
			"name": "tree",
			"posX": 225,
			"posY": 680,
			"posZ": "over"
		},
		{
			"name": "tree",
			"posX": 295,
			"posY": 680,
			"posZ": "over"
		},
		{
			"name": "tree",
			"posX": 365,
			"posY": 680,
			"posZ": "over"
		},
		{
			"name": "tree",
			"posX": 435,
			"posY": 680,
			"posZ": "over"
		},
		{
			"name": "tree",
			"posX": 505,
			"posY": 680,
			"posZ": "over"
		},
		{
			"name": "tree",
			"posX": 575,
			"posY": 680,
			"posZ": "over"
		},
		{
			"name": "tree",
			"posX": 645,
			"posY": 680,
			"posZ": "over"
		},
		{
			"name": "tree",
			"posX": 715,
			"posY": 680,
			"posZ": "over"
		},
		{
			"name": "tree",
			"posX": 785,
			"posY": 680,
			"posZ": "over"
		},
		{
			"name": "tree",
			"posX": 855,
			"posY": 680,
			"posZ": "over"
		},
		{
			"name": "tree",
			"posX": 925,
			"posY": 680,
			"posZ": "over"
		},
		{
			"name": "tree",
			"posX": 995,
			"posY": 680,
			"posZ": "over"
		},
		{
			"name": "tree",
			"posX": 1065,
			"posY": 680,
			"posZ": "over"
		},
		{
			"name": "tree",
			"posX": 1135,
			"posY": 680,
			"posZ": "over"
		},
		{
			"name": "tree",
			"posX": 1205,
			"posY": 680,
			"posZ": "over"
		},
		{
			"name": "tree",
			"posX": 1275,
			"posY": 680,
			"posZ": "over"
		},
		{
			"name": "tree",
			"posX": 1345,
			"posY": 680,
			"posZ": "over"
		},
		{
			"name": "tree",
			"posX": 1415,
			"posY": 680,
			"posZ": "over"
		},
		{
			"name": "tree",
			"posX": 1485,
			"posY": 680,
			"posZ": "over"
		},
		{
			"name": "tree",
			"posX": 1555,
			"posY": 680,
			"posZ": "over"
		},
		{
			"name": "tree",
			"posX": 1625,
			"posY": 680,
			"posZ": "over"
		},
		{
			"name": "tree",
			"posX": 1695,
			"posY": 680,
			"posZ": "over"
		},
		{
			"name": "tree",
			"posX": 1765,
			"posY": 680,
			"posZ": "over"
		},
		{
			"name": "tree",
			"posX": 1835,
			"posY": 680,
			"posZ": "over"
		},
		{
			"name": "tree",
			"posX": 1905,
			"posY": 680,
			"posZ": "over"
		},
		{
			"name": "tree",
			"posX": 1975,
			"posY": 680,
			"posZ": "over"
		},
		{
			"name": "tree",
			"posX": 2045,
			"posY": 680,
			"posZ": "over"
		},
		{
			"name": "tree",
			"posX": 2115,
			"posY": 680,
			"posZ": "over"
		},
		{
			"name": "tree",
			"posX": 2185,
			"posY": 680,
			"posZ": "over"
		},
		{
			"name": "tree",
			"posX": 2255,
			"posY": 680,
			"posZ": "over"
		},
		{
			"name": "tree",
			"posX": 2325,
			"posY": 680,
			"posZ": "over"
		},
		{
			"name": "tree",
			"posX": 2395,
			"posY": 680,
			"posZ": "over"
		},
		{
			"name": "tree",
			"posX": 2465,
			"posY": 680,
			"posZ": "over"
		},
		{
			"name": "tree",
			"posX": 2535,
			"posY": 680,
			"posZ": "over"
		},
		{
			"name": "tree",
			"posX": 2605,
			"posY": 680,
			"posZ": "over"
		},
		{
			"name": "tree",
			"posX": 2675,
			"posY": 680,
			"posZ": "over"
		},
		{
			"name": "tree",
			"posX": 2745,
			"posY": 680,
			"posZ": "over"
		},
		{
			"name": "tree",
			"posX": 2815,
			"posY": 680,
			"posZ": "over"
		},
		{
			"name": "tree",
			"posX": 2885,
			"posY": 680,
			"posZ": "over"
		},
		{
			"name": "tree",
			"posX": 2955,
			"posY": 680,
			"posZ": "over"
		},
		{
			"name": "tree",
			"posX": 3025,
			"posY": 680,
			"posZ": "over"
		},
		{
			"name": "tree",
			"posX": 3095,
			"posY": 680,
			"posZ": "over"
		},
		{
			"name": "tree",
			"posX": 3165,
			"posY": 680,
			"posZ": "over"
		},
		{
			"name": "tree",
			"posX": 3235,
			"posY": 680,
			"posZ": "over"
		},
		{
			"name": "tree",
			"posX": 3305,
			"posY": 680,
			"posZ": "over"
		},
		{
			"name": "tree",
			"posX": 3375,
			"posY": 680,
			"posZ": "over"
		},
		{
			"name": "tree",
			"posX": 3445,
			"posY": 680,
			"posZ": "over"
		},
		{
			"name": "tree",
			"posX": 3515,
			"posY": 680,
			"posZ": "over"
		},
		{
			"name": "tree",
			"posX": 3585,
			"posY": 680,
			"posZ": "over"
		},
		{
			"name": "tree",
			"posX": 3655,
			"posY": 680,
			"posZ": "over"
		},
		{
			"name": "tree",
			"posX": 3725,
			"posY": 680,
			"posZ": "over"
		},
		{
			"name": "tree",
			"posX": 3795,
			"posY": 680,
			"posZ": "over"
		},
		{
			"name": "tree",
			"posX": 3865,
			"posY": 680,
			"posZ": "over"
		},
		{
			"name": "tree",
			"posX": 3935,
			"posY": 680,
			"posZ": "over"
		},
		{
			"name": "tree",
			"posX": 4005,
			"posY": 680,
			"posZ": "over"
		},
		{
			"name": "tree",
			"posX": 4075,
			"posY": 680,
			"posZ": "over"
		},
		{
			"name": "tree",
			"posX": 4145,
			"posY": 680,
			"posZ": "over"
		},
		{
			"name": "tree",
			"posX": 4215,
			"posY": 680,
			"posZ": "over"
		},
		{
			"name": "tree",
			"posX": 4285,
			"posY": 680,
			"posZ": "over"
		},
		{
			"name": "tree",
			"posX": 4355,
			"posY": 680,
			"posZ": "over"
		},
		{
			"name": "tree",
			"posX": 4425,
			"posY": 680,
			"posZ": "over"
		},
		{
			"name": "tree",
			"posX": 4495,
			"posY": 680,
			"posZ": "over"
		},
		{
			"name": "tree",
			"posX": 4565,
			"posY": 680,
			"posZ": "over"
		},
		{
			"name": "tree",
			"posX": 4635,
			"posY": 680,
			"posZ": "over"
		},
		{
			"name": "tree",
			"posX": 4705,
			"posY": 680,
			"posZ": "over"
		},
		{
			"name": "tree",
			"posX": 4775,
			"posY": 680,
			"posZ": "over"
		},
		{
			"name": "tree",
			"posX": 4845,
			"posY": 680,
			"posZ": "over"
		},
		{
			"name": "tree",
			"posX": 4915,
			"posY": 680,
			"posZ": "over"
		},
		{
			"name": "tree",
			"posX": 4985,
			"posY": 680,
			"posZ": "over"
		},
		{
			"name": "tree",
			"posX": 5055,
			"posY": 680,
			"posZ": "over"
		},
		{
			"name": "tree",
			"posX": 5125,
			"posY": 680,
			"posZ": "over"
		},
		{
			"name": "tree",
			"posX": 5195,
			"posY": 680,
			"posZ": "over"
		},
		{
			"name": "tree",
			"posX": 5265,
			"posY": 680,
			"posZ": "over"
		},
		{
			"name": "tree",
			"posX": 5335,
			"posY": 680,
			"posZ": "over"
		},
		{
			"name": "tree",
			"posX": 5405,
			"posY": 680,
			"posZ": "over"
		},
		{
			"name": "tree",
			"posX": 5475,
			"posY": 680,
			"posZ": "over"
		},
		{
			"name": "tree",
			"posX": 5545,
			"posY": 680,
			"posZ": "over"
		},
		{
			"name": "tree",
			"posX": 5615,
			"posY": 680,
			"posZ": "over"
		},
		{
			"name": "tree",
			"posX": 5685,
			"posY": 680,
			"posZ": "over"
		},
		{
			"name": "tree",
			"posX": 5755,
			"posY": 680,
			"posZ": "over"
		},
		{
			"name": "tree",
			"posX": 5825,
			"posY": 680,
			"posZ": "over"
		},
		{
			"name": "tree",
			"posX": 5895,
			"posY": 680,
			"posZ": "over"
		},
		{
			"name": "tree",
			"posX": 5965,
			"posY": 680,
			"posZ": "over"
		},
		{
			"name": "tree",
			"posX": 6035,
			"posY": 680,
			"posZ": "over"
		},
		{
			"name": "tree",
			"posX": 6105,
			"posY": 680,
			"posZ": "over"
		},
		{
			"name": "tree",
			"posX": 6175,
			"posY": 680,
			"posZ": "over"
		},
		{
			"name": "tree",
			"posX": 6245,
			"posY": 680,
			"posZ": "over"
		},
		{
			"name": "tree",
			"posX": 6315,
			"posY": 680,
			"posZ": "over"
		},
		{
			"name": "tree",
			"posX": 6385,
			"posY": 680,
			"posZ": "over"
		},
		{
			"name": "tree",
			"posX": 6455,
			"posY": 680,
			"posZ": "over"
		},
		{
			"name": "tree",
			"posX": 6525,
			"posY": 680,
			"posZ": "over"
		},
		{
			"name": "tree",
			"posX": 6595,
			"posY": 680,
			"posZ": "over"
		},
		{
			"name": "tree",
			"posX": 6665,
			"posY": 680,
			"posZ": "over"
		},
		{
			"name": "tree",
			"posX": 6735,
			"posY": 680,
			"posZ": "over"
		},
		{
			"name": "tree",
			"posX": 6805,
			"posY": 680,
			"posZ": "over"
		},
		{
			"name": "tree",
			"posX": 6875,
			"posY": 680,
			"posZ": "over"
		},
		{
			"name": "tree",
			"posX": 6945,
			"posY": 680,
			"posZ": "over"
		},
		{
			"name": "tree",
			"posX": 7015,
			"posY": 680,
			"posZ": "over"
		}
	]
}
